Workbook

Sheet Parámetros
A1: PARÁMETROS GLOBALES – GLOBAL SOLUTIONS SpA
A3: Parámetro | B3: Valor | C3: Formato/Nota
A4: Rendimiento (km/lt) | B4: 2.5 | C4: 0.0
A5: Precio petróleo ($/lt) | B5: 1300 | C5: $#,##0
A6: Costos fijos ($/viaje) | B6: 50000 | C6: $#,##0
A7: Peajes | B7: Ver columna Peajes por ruta
A8: Provisión mantención ($/viaje) | B8: 30000 | C8: $#,##0
A9: Costo financiero (%) | B9: 0.03 | C9: 0.0%
A10: IVA (%) | B10: 0.19 | C10: 0.0%
A11: Sueldo base chofer ($/día) | B11: 33000 | C11: $#,##0
A12: Comisión chofer (%tarifa orig) | B12: 0.1 | C12: 0.0%
A13: Dist. Coltauco–Casablanca | B13: 188 | C13: #,##0
A15: Celdas azules sobre fondo amarillo = input editable. Cambiar aquí actualiza todos los modelos.

Sheet Peajes Referencia
A1: TARIFAS PEAJE 2026 – CAMIÓN >2 EJES – HORARIO NORMAL
A3: Plaza de Peaje | B3: Ruta | C3: Tramo | D3: Tarifa >2 ejes | E3: Observación
A4: Ruta 68 – Lo Prado | B4: R68 | C4: Casablanca ↔ Santiago | D4: $8.300 | E4: Troncal. 2 troncales en el tramo completo
A5: Ruta 68 – Zapata | B5: R68 | C5: Casablanca ↔ Santiago | D5: $8.300 | E5: Troncal. Se cobran ambos en la mayoría de destinos RM/V
A6: Ruta 68 – Lateral/Troncal Sur | B6: R68 | C6: Ramales y accesos | D6: $3.400 | E6: Tarifa única todo el día
A7: Ruta del Maipo – Angostura | B7: R5 Sur | C7: RM ↔ O'Higgins norte (km54) | D7: $12.200 | E7: Lateral gratis al pagar troncal (6h)
A8: Ruta del Maipo – Quinta | B8: R5 Sur | C8: O'Higgins ↔ Maule norte (km162) | D8: $12.200 | E8: Lateral gratis al pagar troncal (6h)
A9: Ruta del Maipo – Acc. Sur | B9: Acc. Sur | C9: Entrada sur Santiago | D9: $4.400 | E9: Troncal Acceso Sur >2 ejes
A10: Survías – Río Claro | B10: R5 Sur | C10: Maule sur / Talca (km220) | D10: $10.800 | E10: Troncal Survías Talca-Chillán
A11: Survías – Retiro | B11: R5 Sur | C11: Maule sur / Parral (km323) | D11: $10.800 | E11: Troncal Survías
A12: Ruta Sur – Santa Clara | B12: R5 Sur | C12: Ñuble / Bío Bío (km444) | D12: $10.800 | E12: Troncal Ruta Sur

Sheet RM
A1: REGIÓN METROPOLITANA – Base Casablanca | Retorno directo
A2: Verde=peaje real integrado | Naranja=tarifa nueva | Amarillo=input manual | Comisión=10% tarifa original
A3: Región | B3: Destino | C3: DISTANCIAS (km) | F3: Tarifa Original ($) | G3: Comisión Chofer 10% ($) | H3: Viatico Conductor | I3: Tarifa Nueva ($) | J3: Tarifa +IVA ($) | K3: Gasto Petróleo ($) | L3: Costos Fijos ($) | M3: Peajes I+V ($) | N3: Costo Financiero ($) | O3: Prov. Mant. ($) | P3: Días Chofer | Q3: Sueldo Base ($) | R3: Costo Total ($) | S3: Costo/km ($) | T3: Tarifa/km ($) | U3: Margen Op. ($) | V3: Margen Bruto % | W3: Margen Neto %
C4: Km Ida | D4: Km Vuelta | E4: Km Total
A5: RM | B5: ALHUE | C5: 75 | D5: 75 | E5: =C5+D5 -> 150 | F5: 300000 | G5: =F5*Parámetros!$B$12 -> 30000 | H5: 12000 | I5: 354000 | J5: =I5*(1+Parámetros!$B$10) -> 421260 | K5: =E5/Parámetros!$B$4*Parámetros!$B$5 -> 78000 | L5: =Parámetros!$B$6 -> 50000 | M5: 0 | N5: =J5*Parámetros!$B$9 -> 12637.8 | O5: =Parámetros!$B$8 -> 30000 | P5: 1 | Q5: =IF(P5="",0,P5*Parámetros!$B$11) -> 33000 | R5: =K5+L5+M5+N5+O5+Q5 -> 203637.8 | S5: =IF(E5=0,"",R5/E5) -> 1357.5853 | T5: =IF(E5=0,"",I5/E5) -> 2360 | U5: =I5-R5 -> 150362.2 | V5: =IF(I5=0,"",(I5-K5-L5-M5-O5)/I5) -> 0.55367232 | W5: =IF(I5=0,"",U5/I5) -> 0.42475198
A6: RM | B6: BUIN | C6: 88 | D6: 88 | E6: =C6+D6 -> 176 | F6: 300000 | G6: =F6*Parámetros!$B$12 -> 30000 | H6: 12000 | I6: 354000 | J6: =I6*(1+Parámetros!$B$10) -> 421260 | K6: =E6/Parámetros!$B$4*Parámetros!$B$5 -> 91520 | L6: =Parámetros!$B$6 -> 50000 | M6: 20000 | N6: =J6*Parámetros!$B$9 -> 12637.8 | O6: =Parámetros!$B$8 -> 30000 | P6: 1 | Q6: =IF(P6="",0,P6*Parámetros!$B$11) -> 33000 | R6: =K6+L6+M6+N6+O6+Q6 -> 237157.8 | S6: =IF(E6=0,"",R6/E6) -> 1347.4875 | T6: =IF(E6=0,"",I6/E6) -> 2011.3636 | U6: =I6-R6 -> 116842.2 | V6: =IF(I6=0,"",(I6-K6-L6-M6-O6)/I6) -> 0.45898305 | W6: =IF(I6=0,"",U6/I6) -> 0.33006271
A7: RM | B7: COLINA | C7: 93 | D7: 93 | E7: =C7+D7 -> 186 | F7: 300000 | G7: =F7*Parámetros!$B$12 -> 30000 | H7: 12000 | I7: 354000 | J7: =I7*(1+Parámetros!$B$10) -> 421260 | K7: =E7/Parámetros!$B$4*Parámetros!$B$5 -> 96720 | L7: =Parámetros!$B$6 -> 50000 | M7: 33200 | N7: =J7*Parámetros!$B$9 -> 12637.8 | O7: =Parámetros!$B$8 -> 30000 | P7: 1 | Q7: =IF(P7="",0,P7*Parámetros!$B$11) -> 33000 | R7: =K7+L7+M7+N7+O7+Q7 -> 255557.8 | S7: =IF(E7=0,"",R7/E7) -> 1373.9667 | T7: =IF(E7=0,"",I7/E7) -> 1903.2258 | U7: =I7-R7 -> 98442.2 | V7: =IF(I7=0,"",(I7-K7-L7-M7-O7)/I7) -> 0.40700565 | W7: =IF(I7=0,"",U7/I7) -> 0.27808531
A8: RM | B8: CURACAVI | C8: 34 | D8: 34 | E8: =C8+D8 -> 68 | F8: 280000 | G8: =F8*Parámetros!$B$12 -> 28000 | H8: 12000 | I8: 330400 | J8: =I8*(1+Parámetros!$B$10) -> 393176 | K8: =E8/Parámetros!$B$4*Parámetros!$B$5 -> 35360 | L8: =Parámetros!$B$6 -> 50000 | M8: 0 | N8: =J8*Parámetros!$B$9 -> 11795.28 | O8: =Parámetros!$B$8 -> 30000 | P8: 1 | Q8: =IF(P8="",0,P8*Parámetros!$B$11) -> 33000 | R8: =K8+L8+M8+N8+O8+Q8 -> 160155.28 | S8: =IF(E8=0,"",R8/E8) -> 2355.2247 | T8: =IF(E8=0,"",I8/E8) -> 4858.8235 | U8: =I8-R8 -> 170244.72 | V8: =IF(I8=0,"",(I8-K8-L8-M8-O8)/I8) -> 0.65084746 | W8: =IF(I8=0,"",U8/I8) -> 0.51526852
A9: RM | B9: EL MONTE | C9: 75 | D9: 75 | E9: =C9+D9 -> 150 | F9: 300000 | G9: =F9*Parámetros!$B$12 -> 30000 | H9: 12000 | I9: 354000 | J9: =I9*(1+Parámetros!$B$10) -> 421260 | K9: =E9/Parámetros!$B$4*Parámetros!$B$5 -> 78000 | L9: =Parámetros!$B$6 -> 50000 | M9: 33200 | N9: =J9*Parámetros!$B$9 -> 12637.8 | O9: =Parámetros!$B$8 -> 30000 | P9: 1 | Q9: =IF(P9="",0,P9*Parámetros!$B$11) -> 33000 | R9: =K9+L9+M9+N9+O9+Q9 -> 236837.8 | S9: =IF(E9=0,"",R9/E9) -> 1578.9187 | T9: =IF(E9=0,"",I9/E9) -> 2360 | U9: =I9-R9 -> 117162.2 | V9: =IF(I9=0,"",(I9-K9-L9-M9-O9)/I9) -> 0.45988701 | W9: =IF(I9=0,"",U9/I9) -> 0.33096667
A10: RM | B10: ISLA MAIPO | C10: 75 | D10: 75 | E10: =C10+D10 -> 150 | F10: 300000 | G10: =F10*Parámetros!$B$12 -> 30000 | H10: 12000 | I10: 354000 | J10: =I10*(1+Parámetros!$B$10) -> 421260 | K10: =E10/Parámetros!$B$4*Parámetros!$B$5 -> 78000 | L10: =Parámetros!$B$6 -> 50000 | M10: 33200 | N10: =J10*Parámetros!$B$9 -> 12637.8 | O10: =Parámetros!$B$8 -> 30000 | P10: 1 | Q10: =IF(P10="",0,P10*Parámetros!$B$11) -> 33000 | R10: =K10+L10+M10+N10+O10+Q10 -> 236837.8 | S10: =IF(E10=0,"",R10/E10) -> 1578.9187 | T10: =IF(E10=0,"",I10/E10) -> 2360 | U10: =I10-R10 -> 117162.2 | V10: =IF(I10=0,"",(I10-K10-L10-M10-O10)/I10) -> 0.45988701 | W10: =IF(I10=0,"",U10/I10) -> 0.33096667
A11: RM | B11: LAMPA | C11: 93 | D11: 93 | E11: =C11+D11 -> 186 | F11: 280000 | G11: =F11*Parámetros!$B$12 -> 28000 | H11: 12000 | I11: 330400 | J11: =I11*(1+Parámetros!$B$10) -> 393176 | K11: =E11/Parámetros!$B$4*Parámetros!$B$5 -> 96720 | L11: =Parámetros!$B$6 -> 50000 | M11: 33200 | N11: =J11*Parámetros!$B$9 -> 11795.28 | O11: =Parámetros!$B$8 -> 30000 | P11: 1 | Q11: =IF(P11="",0,P11*Parámetros!$B$11) -> 33000 | R11: =K11+L11+M11+N11+O11+Q11 -> 254715.28 | S11: =IF(E11=0,"",R11/E11) -> 1369.437 | T11: =IF(E11=0,"",I11/E11) -> 1776.3441 | U11: =I11-R11 -> 75684.72 | V11: =IF(I11=0,"",(I11-K11-L11-M11-O11)/I11) -> 0.36464891 | W11: =IF(I11=0,"",U11/I11) -> 0.22906998
A12: RM | B12: MARIA PINTO | C12: 56 | D12: 56 | E12: =C12+D12 -> 112 | F12: 280000 | G12: =F12*Parámetros!$B$12 -> 28000 | H12: 12000 | I12: 330400 | J12: =I12*(1+Parámetros!$B$10) -> 393176 | K12: =E12/Parámetros!$B$4*Parámetros!$B$5 -> 58240 | L12: =Parámetros!$B$6 -> 50000 | M12: 0 | N12: =J12*Parámetros!$B$9 -> 11795.28 | O12: =Parámetros!$B$8 -> 30000 | P12: 1 | Q12: =IF(P12="",0,P12*Parámetros!$B$11) -> 33000 | R12: =K12+L12+M12+N12+O12+Q12 -> 183035.28 | S12: =IF(E12=0,"",R12/E12) -> 1634.2436 | T12: =IF(E12=0,"",I12/E12) -> 2950 | U12: =I12-R12 -> 147364.72 | V12: =IF(I12=0,"",(I12-K12-L12-M12-O12)/I12) -> 0.58159806 | W12: =IF(I12=0,"",U12/I12) -> 0.44601913
A13: RM | B13: PAINE | C13: 88 | D13: 88 | E13: =C13+D13 -> 176 | F13: 300000 | G13: =F13*Parámetros!$B$12 -> 30000 | H13: 12000 | I13: 354000 | J13: =I13*(1+Parámetros!$B$10) -> 421260 | K13: =E13/Parámetros!$B$4*Parámetros!$B$5 -> 91520 | L13: =Parámetros!$B$6 -> 50000 | M13: 39800 | N13: =J13*Parámetros!$B$9 -> 12637.8 | O13: =Parámetros!$B$8 -> 30000 | P13: 1 | Q13: =IF(P13="",0,P13*Parámetros!$B$11) -> 33000 | R13: =K13+L13+M13+N13+O13+Q13 -> 256957.8 | S13: =IF(E13=0,"",R13/E13) -> 1459.9875 | T13: =IF(E13=0,"",I13/E13) -> 2011.3636 | U13: =I13-R13 -> 97042.2 | V13: =IF(I13=0,"",(I13-K13-L13-M13-O13)/I13) -> 0.40305085 | W13: =IF(I13=0,"",U13/I13) -> 0.27413051
A14: RM | B14: PEÑAFLOR | C14: 75 | D14: 75 | E14: =C14+D14 -> 150 | F14: 300000 | G14: =F14*Parámetros!$B$12 -> 30000 | H14: 12000 | I14: 354000 | J14: =I14*(1+Parámetros!$B$10) -> 421260 | K14: =E14/Parámetros!$B$4*Parámetros!$B$5 -> 78000 | L14: =Parámetros!$B$6 -> 50000 | M14: 33200 | N14: =J14*Parámetros!$B$9 -> 12637.8 | O14: =Parámetros!$B$8 -> 30000 | P14: 1 | Q14: =IF(P14="",0,P14*Parámetros!$B$11) -> 33000 | R14: =K14+L14+M14+N14+O14+Q14 -> 236837.8 | S14: =IF(E14=0,"",R14/E14) -> 1578.9187 | T14: =IF(E14=0,"",I14/E14) -> 2360 | U14: =I14-R14 -> 117162.2 | V14: =IF(I14=0,"",(I14-K14-L14-M14-O14)/I14) -> 0.45988701 | W14: =IF(I14=0,"",U14/I14) -> 0.33096667
A15: RM | B15: POMAIRE | C15: 87 | D15: 87 | E15: =C15+D15 -> 174 | F15: 280000 | G15: =F15*Parámetros!$B$12 -> 28000 | H15: 12000 | I15: 330400 | J15: =I15*(1+Parámetros!$B$10) -> 393176 | K15: =E15/Parámetros!$B$4*Parámetros!$B$5 -> 90480 | L15: =Parámetros!$B$6 -> 50000 | M15: 0 | N15: =J15*Parámetros!$B$9 -> 11795.28 | O15: =Parámetros!$B$8 -> 30000 | P15: 1 | Q15: =IF(P15="",0,P15*Parámetros!$B$11) -> 33000 | R15: =K15+L15+M15+N15+O15+Q15 -> 215275.28 | S15: =IF(E15=0,"",R15/E15) -> 1237.2143 | T15: =IF(E15=0,"",I15/E15) -> 1898.8506 | U15: =I15-R15 -> 115124.72 | V15: =IF(I15=0,"",(I15-K15-L15-M15-O15)/I15) -> 0.48401937 | W15: =IF(I15=0,"",U15/I15) -> 0.34844044
A16: RM | B16: SAN BERNARDO | C16: 88 | D16: 88 | E16: =C16+D16 -> 176 | F16: 300000 | G16: =F16*Parámetros!$B$12 -> 30000 | H16: 12000 | I16: 354000 | J16: =I16*(1+Parámetros!$B$10) -> 421260 | K16: =E16/Parámetros!$B$4*Parámetros!$B$5 -> 91520 | L16: =Parámetros!$B$6 -> 50000 | M16: 39800 | N16: =J16*Parámetros!$B$9 -> 12637.8 | O16: =Parámetros!$B$8 -> 30000 | P16: 1 | Q16: =IF(P16="",0,P16*Parámetros!$B$11) -> 33000 | R16: =K16+L16+M16+N16+O16+Q16 -> 256957.8 | S16: =IF(E16=0,"",R16/E16) -> 1459.9875 | T16: =IF(E16=0,"",I16/E16) -> 2011.3636 | U16: =I16-R16 -> 97042.2 | V16: =IF(I16=0,"",(I16-K16-L16-M16-O16)/I16) -> 0.40305085 | W16: =IF(I16=0,"",U16/I16) -> 0.27413051
... A19: RM | B19: PADRE HURTADO | C19: 89 | D19: 89 | E19: =C19+D19 -> 178 | F19: 280000 | G19: =F19*Parámetros!$B$12 -> 28000 | H19: 12000 | I19: 330400 | J19: =I19*(1+Parámetros!$B$10) -> 393176 | K19: =E19/Parámetros!$B$4*Parámetros!$B$5 -> 92560 | L19: =Parámetros!$B$6 -> 50000 | M19: 33200 | N19: =J19*Parámetros!$B$9 -> 11795.28 | O19: =Parámetros!$B$8 -> 30000 | P19: 1 | Q19: =IF(P19="",0,P19*Parámetros!$B$11) -> 33000 | R19: =K19+L19+M19+N19+O19+Q19 -> 250555.28 | S19: =IF(E19=0,"",R19/E19) -> 1407.6139 | T19: =IF(E19=0,"",I19/E19) -> 1856.1798 | U19: =I19-R19 -> 79844.72 | V19: =IF(I19=0,"",(I19-K19-L19-M19-O19)/I19) -> 0.37723971 | W19: =IF(I19=0,"",U19/I19) -> 0.24166077

Sheet V Valparaíso
A1: REGIÓN DE VALPARAÍSO – Base Casablanca | Retorno directo
A2: Verde=peaje real integrado | Naranja=tarifa nueva | Amarillo=input manual | Comisión=10% tarifa original
A3: Región | B3: Destino | C3: DISTANCIAS (km) | F3: Tarifa Original ($) | G3: Comisión Chofer 10% ($) | H3: Viatico Conductor | I3: Tarifa Nueva ($) | J3: Tarifa +IVA ($) | K3: Gasto Petróleo ($) | L3: Costos Fijos ($) | M3: Peajes I+V ($) | N3: Costo Financiero ($) | O3: Prov. Mant. ($) | P3: Días Chofer | Q3: Sueldo Base ($) | R3: Costo Total ($) | S3: Costo/km ($) | T3: Tarifa/km ($) | U3: Margen Op. ($) | V3: Margen Bruto % | W3: Margen Neto %
C4: Km Ida | D4: Km Vuelta | E4: Km Total
A5: V Valparaíso | B5: CABILDO | C5: 110 | D5: 110 | E5: =C5+D5 -> 220 | F5: 380000 | G5: =F5*Parámetros!$B$12 -> 38000 | H5: 12000 | I5: 448400 | J5: =I5*(1+Parámetros!$B$10) -> 533596 | K5: =E5/Parámetros!$B$4*Parámetros!$B$5 -> 114400 | L5: =Parámetros!$B$6 -> 50000 | M5: 39800 | N5: =J5*Parámetros!$B$9 -> 16007.88 | O5: =Parámetros!$B$8 -> 30000 | P5: 1 | Q5: =IF(P5="",0,P5*Parámetros!$B$11) -> 33000 | R5: =K5+L5+M5+N5+O5+Q5 -> 283207.88 | S5: =IF(E5=0,"",R5/E5) -> 1287.3085 | T5: =IF(E5=0,"",I5/E5) -> 2038.1818 | U5: =I5-R5 -> 165192.12 | V5: =IF(I5=0,"",(I5-K5-L5-M5-O5)/I5) -> 0.47769848 | W5: =IF(I5=0,"",U5/I5) -> 0.36840348
A6: V Valparaíso | B6: CALLE LARGA | C6: 87 | D6: 87 | E6: =C6+D6 -> 174 | F6: 380000 | G6: =F6*Parámetros!$B$12 -> 38000 | H6: 12000 | I6: 448400 | J6: =I6*(1+Parámetros!$B$10) -> 533596 | K6: =E6/Parámetros!$B$4*Parámetros!$B$5 -> 90480 | L6: =Parámetros!$B$6 -> 50000 | M6: 33200 | N6: =J6*Parámetros!$B$9 -> 16007.88 | O6: =Parámetros!$B$8 -> 30000 | P6: 1 | Q6: =IF(P6="",0,P6*Parámetros!$B$11) -> 33000 | R6: =K6+L6+M6+N6+O6+Q6 -> 252687.88 | S6: =IF(E6=0,"",R6/E6) -> 1452.2292 | T6: =IF(E6=0,"",I6/E6) -> 2577.0115 | U6: =I6-R6 -> 195712.12 | V6: =IF(I6=0,"",(I6-K6-L6-M6-O6)/I6) -> 0.54576271 | W6: =IF(I6=0,"",U6/I6) -> 0.43646771
A7: V Valparaíso | B7: CASABLANCA | C7: 0 | D7: 0 | E7: =C7+D7 -> 0 | F7: 280000 | G7: =F7*Parámetros!$B$12 -> 28000 | H7: 12000 | I7: 330400 | J7: =I7*(1+Parámetros!$B$10) -> 393176 | K7: =E7/Parámetros!$B$4*Parámetros!$B$5 -> 0 | L7: =Parámetros!$B$6 -> 50000 | M7: 0 | N7: =J7*Parámetros!$B$9 -> 11795.28 | O7: =Parámetros!$B$8 -> 30000 | P7: 1 | Q7: =IF(P7="",0,P7*Parámetros!$B$11) -> 33000 | R7: =K7+L7+M7+N7+O7+Q7 -> 124795.28 | S7: =IF(E7=0,"",R7/E7) | T7: =IF(E7=0,"",I7/E7) | U7: =I7-R7 -> 205604.72 | V7: =IF(I7=0,"",(I7-K7-L7-M7-O7)/I7) -> 0.75786925 | W7: =IF(I7=0,"",U7/I7) -> 0.62229031
A8: V Valparaíso | B8: HIJUELA | C8: 75 | D8: 75 | E8: =C8+D8 -> 150 | F8: 380000 | G8: =F8*Parámetros!$B$12 -> 38000 | H8: 12000 | I8: 448400 | J8: =I8*(1+Parámetros!$B$10) -> 533596 | K8: =E8/Parámetros!$B$4*Parámetros!$B$5 -> 78000 | L8: =Parámetros!$B$6 -> 50000 | M8: 33200 | N8: =J8*Parámetros!$B$9 -> 16007.88 | O8: =Parámetros!$B$8 -> 30000 | P8: 1 | Q8: =IF(P8="",0,P8*Parámetros!$B$11) -> 33000 | R8: =K8+L8+M8+N8+O8+Q8 -> 240207.88 | S8: =IF(E8=0,"",R8/E8) -> 1601.3859 | T8: =IF(E8=0,"",I8/E8) -> 2989.3333 | U8: =I8-R8 -> 208192.12 | V8: =IF(I8=0,"",(I8-K8-L8-M8-O8)/I8) -> 0.573595 | W8: =IF(I8=0,"",U8/I8) -> 0.4643
A9: V Valparaíso | B9: LA LIGUA | C9: 120 | D9: 120 | E9: =C9+D9 -> 240 | F9: 380000 | G9: =F9*Parámetros!$B$12 -> 38000 | H9: 12000 | I9: 448400 | J9: =I9*(1+Parámetros!$B$10) -> 533596 | K9: =E9/Parámetros!$B$4*Parámetros!$B$5 -> 124800 | L9: =Parámetros!$B$6 -> 50000 | M9: 39800 | N9: =J9*Parámetros!$B$9 -> 16007.88 | O9: =Parámetros!$B$8 -> 30000 | P9: 1 | Q9: =IF(P9="",0,P9*Parámetros!$B$11) -> 33000 | R9: =K9+L9+M9+N9+O9+Q9 -> 293607.88 | S9: =IF(E9=0,"",R9/E9) -> 1223.3662 | T9: =IF(E9=0,"",I9/E9) -> 1868.3333 | U9: =I9-R9 -> 154792.12 | V9: =IF(I9=0,"",(I9-K9-L9-M9-O9)/I9) -> 0.45450491 | W9: =IF(I9=0,"",U9/I9) -> 0.3452099
A10: V Valparaíso | B10: LLAILLAY | C10: 85 | D10: 85 | E10: =C10+D10 -> 170 | F10: 380000 | G10: =F10*Parámetros!$B$12 -> 38000 | H10: 12000 | I10: 448400 | J10: =I10*(1+Parámetros!$B$10) -> 533596 | K10: =E10/Parámetros!$B$4*Parámetros!$B$5 -> 88400 | L10: =Parámetros!$B$6 -> 50000 | M10: 33200 | N10: =J10*Parámetros!$B$9 -> 16007.88 | O10: =Parámetros!$B$8 -> 30000 | P10: 1 | Q10: =IF(P10="",0,P10*Parámetros!$B$11) -> 33000 | R10: =K10+L10+M10+N10+O10+Q10 -> 250607.88 | S10: =IF(E10=0,"",R10/E10) -> 1474.164 | T10: =IF(E10=0,"",I10/E10) -> 2637.6471 | U10: =I10-R10 -> 197792.12 | V10: =IF(I10=0,"",(I10-K10-L10-M10-O10)/I10) -> 0.55040143 | W10: =IF(I10=0,"",U10/I10) -> 0.44110642
A11: V Valparaíso | B11: LOS ANDES | C11: 87 | D11: 87 | E11: =C11+D11 -> 174 | F11: 380000 | G11: =F11*Parámetros!$B$12 -> 38000 | H11: 12000 | I11: 448400 | J11: =I11*(1+Parámetros!$B$10) -> 533596 | K11: =E11/Parámetros!$B$4*Parámetros!$B$5 -> 90480 | L11: =Parámetros!$B$6 -> 50000 | M11: 33200 | N11: =J11*Parámetros!$B$9 -> 16007.88 | O11: =Parámetros!$B$8 -> 30000 | P11: 1 | Q11: =IF(P11="",0,P11*Parámetros!$B$11) -> 33000 | R11: =K11+L11+M11+N11+O11+Q11 -> 252687.88 | S11: =IF(E11=0,"",R11/E11) -> 1452.2292 | T11: =IF(E11=0,"",I11/E11) -> 2577.0115 | U11: =I11-R11 -> 195712.12 | V11: =IF(I11=0,"",(I11-K11-L11-M11-O11)/I11) -> 0.54576271 | W11: =IF(I11=0,"",U11/I11) -> 0.43646771
A12: V Valparaíso | B12: PANQUEHUE | C12: 75 | D12: 75 | E12: =C12+D12 -> 150 | F12: 380000 | G12: =F12*Parámetros!$B$12 -> 38000 | H12: 12000 | I12: 448400 | J12: =I12*(1+Parámetros!$B$10) -> 533596 | K12: =E12/Parámetros!$B$4*Parámetros!$B$5 -> 78000 | L12: =Parámetros!$B$6 -> 50000 | M12: 33200 | N12: =J12*Parámetros!$B$9 -> 16007.88 | O12: =Parámetros!$B$8 -> 30000 | P12: 1 | Q12: =IF(P12="",0,P12*Parámetros!$B$11) -> 33000 | R12: =K12+L12+M12+N12+O12+Q12 -> 240207.88 | S12: =IF(E12=0,"",R12/E12) -> 1601.3859 | T12: =IF(E12=0,"",I12/E12) -> 2989.3333 | U12: =I12-R12 -> 208192.12 | V12: =IF(I12=0,"",(I12-K12-L12-M12-O12)/I12) -> 0.573595 | W12: =IF(I12=0,"",U12/I12) -> 0.4643
A13: V Valparaíso | B13: PETORCA | C13: 130 | D13: 130 | E13: =C13+D13 -> 260 | F13: 400000 | G13: =F13*Parámetros!$B$12 -> 40000 | H13: 12000 | I13: 472000 | J13: =I13*(1+Parámetros!$B$10) -> 561680 | K13: =E13/Parámetros!$B$4*Parámetros!$B$5 -> 135200 | L13: =Parámetros!$B$6 -> 50000 | M13: 46400 | N13: =J13*Parámetros!$B$9 -> 16850.4 | O13: =Parámetros!$B$8 -> 30000 | P13: 1 | Q13: =IF(P13="",0,P13*Parámetros!$B$11) -> 33000 | R13: =K13+L13+M13+N13+O13+Q13 -> 311450.4 | S13: =IF(E13=0,"",R13/E13) -> 1197.8862 | T13: =IF(E13=0,"",I13/E13) -> 1815.3846 | U13: =I13-R13 -> 160549.6 | V13: =IF(I13=0,"",(I13-K13-L13-M13-O13)/I13) -> 0.44576271 | W13: =IF(I13=0,"",U13/I13) -> 0.34014746
A14: V Valparaíso | B14: PUTAENDO | C14: 90 | D14: 90 | E14: =C14+D14 -> 180 | F14: 380000 | G14: =F14*Parámetros!$B$12 -> 38000 | H14: 12000 | I14: 448400 | J14: =I14*(1+Parámetros!$B$10) -> 533596 | K14: =E14/Parámetros!$B$4*Parámetros!$B$5 -> 93600 | L14: =Parámetros!$B$6 -> 50000 | M14: 39800 | N14: =J14*Parámetros!$B$9 -> 16007.88 | O14: =Parámetros!$B$8 -> 30000 | P14: 1 | Q14: =IF(P14="",0,P14*Parámetros!$B$11) -> 33000 | R14: =K14+L14+M14+N14+O14+Q14 -> 262407.88 | S14: =IF(E14=0,"",R14/E14) -> 1457.8216 | T14: =IF(E14=0,"",I14/E14) -> 2491.1111 | U14: =I14-R14 -> 185992.12 | V14: =IF(I14=0,"",(I14-K14-L14-M14-O14)/I14) -> 0.52408564 | W14: =IF(I14=0,"",U14/I14) -> 0.41479063
A15: V Valparaíso | B15: QUILLOTA | C15: 65 | D15: 65 | E15: =C15+D15 -> 130 | F15: 380000 | G15: =F15*Parámetros!$B$12 -> 38000 | H15: 12000 | I15: 448400 | J15: =I15*(1+Parámetros!$B$10) -> 533596 | K15: =E15/Parámetros!$B$4*Parámetros!$B$5 -> 67600 | L15: =Parámetros!$B$6 -> 50000 | M15: 16600 | N15: =J15*Parámetros!$B$9 -> 16007.88 | O15: =Parámetros!$B$8 -> 30000 | P15: 1 | Q15: =IF(P15="",0,P15*Parámetros!$B$11) -> 33000 | R15: =K15+L15+M15+N15+O15+Q15 -> 213207.88 | S15: =IF(E15=0,"",R15/E15) -> 1640.0606 | T15: =IF(E15=0,"",I15/E15) -> 3449.2308 | U15: =I15-R15 -> 235192.12 | V15: =IF(I15=0,"",(I15-K15-L15-M15-O15)/I15) -> 0.6338091 | W15: =IF(I15=0,"",U15/I15) -> 0.52451409
A16: V Valparaíso | B16: RINCONADA | C16: 80 | D16: 80 | E16: =C16+D16 -> 160 | F16: 380000 | G16: =F16*Parámetros!$B$12 -> 38000 | H16: 12000 | I16: 448400 | J16: =I16*(1+Parámetros!$B$10) -> 533596 | K16: =E16/Parámetros!$B$4*Parámetros!$B$5 -> 83200 | L16: =Parámetros!$B$6 -> 50000 | M16: 33200 | N16: =J16*Parámetros!$B$9 -> 16007.88 | O16: =Parámetros!$B$8 -> 30000 | P16: 1 | Q16: =IF(P16="",0,P16*Parámetros!$B$11) -> 33000 | R16: =K16+L16+M16+N16+O16+Q16 -> 245407.88 | S16: =IF(E16=0,"",R16/E16) -> 1533.7993 | T16: =IF(E16=0,"",I16/E16) -> 2802.5 | U16: =I16-R16 -> 202992.12 | V16: =IF(I16=0,"",(I16-K16-L16-M16-O16)/I16) -> 0.56199822 | W16: =IF(I16=0,"",U16/I16) -> 0.45270321
... A21: V Valparaíso | B21: VALPARAISO | C21: 55 | D21: 55 | E21: =C21+D21 -> 110 | F21: 280000 | G21: =F21*Parámetros!$B$12 -> 28000 | H21: 12000 | I21: 330400 | J21: =I21*(1+Parámetros!$B$10) -> 393176 | K21: =E21/Parámetros!$B$4*Parámetros!$B$5 -> 57200 | L21: =Parámetros!$B$6 -> 50000 | M21: 16600 | N21: =J21*Parámetros!$B$9 -> 11795.28 | O21: =Parámetros!$B$8 -> 30000 | P21: 1 | Q21: =IF(P21="",0,P21*Parámetros!$B$11) -> 33000 | R21: =K21+L21+M21+N21+O21+Q21 -> 198595.28 | S21: =IF(E21=0,"",R21/E21) -> 1805.4116 | T21: =IF(E21=0,"",I21/E21) -> 3003.6364 | U21: =I21-R21 -> 131804.72 | V21: =IF(I21=0,"",(I21-K21-L21-M21-O21)/I21) -> 0.53450363 | W21: =IF(I21=0,"",U21/I21) -> 0.3989247

Sheet VI O'Higgins
A1: REGIÓN O'HIGGINS – Base Coltauco (vía Casablanca 188km)
A2: Verde=peaje real integrado | Naranja=tarifa nueva | Amarillo=input manual | Comisión=10% tarifa original
A3: Región | B3: Destino | C3: DISTANCIAS (km) | F3: Tarifa Original ($) | G3: Comisión Chofer 10% ($) | H3: Viatico Conductor | I3: Tarifa Nueva ($) | J3: Tarifa +IVA ($) | K3: Gasto Petróleo ($) | L3: Costos Fijos ($) | M3: Peajes I+V ($) | N3: Costo Financiero ($) | O3: Prov. Mant. ($) | P3: Días Chofer | Q3: Sueldo Base ($) | R3: Costo Total ($) | S3: Costo/km ($) | T3: Tarifa/km ($) | U3: Margen Op. ($) | V3: Margen Bruto % | W3: Margen Neto %
C4: Km Ida | D4: Km Vuelta | E4: Km Total
A5: VI O'Higgins | B5: LITUECHE | C5: 295 | D5: 130 | E5: =C5+D5 -> 425 | F5: 370000 | G5: =F5*Parámetros!$B$12 -> 37000 | H5: 12000 | I5: 473600 | J5: =I5*(1+Parámetros!$B$10) -> 563584 | K5: =E5/Parámetros!$B$4*Parámetros!$B$5 -> 221000 | L5: =Parámetros!$B$6 -> 50000 | M5: 50000 | N5: =J5*Parámetros!$B$9 -> 16907.52 | O5: =Parámetros!$B$8 -> 30000 | P5: 1 | Q5: =IF(P5="",0,P5*Parámetros!$B$11) -> 33000 | R5: =K5+L5+M5+N5+O5+Q5 -> 400907.52 | S5: =IF(E5=0,"",R5/E5) -> 943.31181 | T5: =IF(E5=0,"",I5/E5) -> 1114.3529 | U5: =I5-R5 -> 72692.48 | V5: =IF(I5=0,"",(I5-K5-L5-M5-O5)/I5) -> 0.25886824 | W5: =IF(I5=0,"",U5/I5) -> 0.15348919
A6: VI O'Higgins | B6: ROSARIO | C6: 244 | D6: 178 | E6: =C6+D6 -> 422 | F6: 370000 | G6: =F6*Parámetros!$B$12 -> 37000 | H6: 12000 | I6: 473600 | J6: =I6*(1+Parámetros!$B$10) -> 563584 | K6: =E6/Parámetros!$B$4*Parámetros!$B$5 -> 219440 | L6: =Parámetros!$B$6 -> 50000 | M6: 50000 | N6: =J6*Parámetros!$B$9 -> 16907.52 | O6: =Parámetros!$B$8 -> 30000 | P6: 1 | Q6: =IF(P6="",0,P6*Parámetros!$B$11) -> 33000 | R6: =K6+L6+M6+N6+O6+Q6 -> 399347.52 | S6: =IF(E6=0,"",R6/E6) -> 946.32114 | T6: =IF(E6=0,"",I6/E6) -> 1122.2749 | U6: =I6-R6 -> 74252.48 | V6: =IF(I6=0,"",(I6-K6-L6-M6-O6)/I6) -> 0.26216216 | W6: =IF(I6=0,"",U6/I6) -> 0.15678311
A7: VI O'Higgins | B7: GRANEROS | C7: 235 | D7: 144 | E7: =C7+D7 -> 379 | F7: 370000 | G7: =F7*Parámetros!$B$12 -> 37000 | H7: 12000 | I7: 473600 | J7: =I7*(1+Parámetros!$B$10) -> 563584 | K7: =E7/Parámetros!$B$4*Parámetros!$B$5 -> 197080 | L7: =Parámetros!$B$6 -> 50000 | M7: 50000 | N7: =J7*Parámetros!$B$9 -> 16907.52 | O7: =Parámetros!$B$8 -> 30000 | P7: 1 | Q7: =IF(P7="",0,P7*Parámetros!$B$11) -> 33000 | R7: =K7+L7+M7+N7+O7+Q7 -> 376987.52 | S7: =IF(E7=0,"",R7/E7) -> 994.69003 | T7: =IF(E7=0,"",I7/E7) -> 1249.6042 | U7: =I7-R7 -> 96612.48 | V7: =IF(I7=0,"",(I7-K7-L7-M7-O7)/I7) -> 0.309375 | W7: =IF(I7=0,"",U7/I7) -> 0.20399595
A8: VI O'Higgins | B8: RANCAGUA | C8: 227 | D8: 154 | E8: =C8+D8 -> 381 | F8: 400000 | G8: =F8*Parámetros!$B$12 -> 40000 | H8: 12000 | I8: 512000 | J8: =I8*(1+Parámetros!$B$10) -> 609280 | K8: =E8/Parámetros!$B$4*Parámetros!$B$5 -> 198120 | L8: =Parámetros!$B$6 -> 50000 | M8: 50000 | N8: =J8*Parámetros!$B$9 -> 18278.4 | O8: =Parámetros!$B$8 -> 30000 | P8: 1 | Q8: =IF(P8="",0,P8*Parámetros!$B$11) -> 33000 | R8: =K8+L8+M8+N8+O8+Q8 -> 379398.4 | S8: =IF(E8=0,"",R8/E8) -> 995.79633 | T8: =IF(E8=0,"",I8/E8) -> 1343.832 | U8: =I8-R8 -> 132601.6 | V8: =IF(I8=0,"",(I8-K8-L8-M8-O8)/I8) -> 0.35914062 | W8: =IF(I8=0,"",U8/I8) -> 0.2589875
A9: VI O'Higgins | B9: LAS CABRAS | C9: 227 | D9: 140 | E9: =C9+D9 -> 367 | F9: 370000 | G9: =F9*Parámetros!$B$12 -> 37000 | H9: 12000 | I9: 473600 | J9: =I9*(1+Parámetros!$B$10) -> 563584 | K9: =E9/Parámetros!$B$4*Parámetros!$B$5 -> 190840 | L9: =Parámetros!$B$6 -> 50000 | M9: 50000 | N9: =J9*Parámetros!$B$9 -> 16907.52 | O9: =Parámetros!$B$8 -> 30000 | P9: 1 | Q9: =IF(P9="",0,P9*Parámetros!$B$11) -> 33000 | R9: =K9+L9+M9+N9+O9+Q9 -> 370747.52 | S9: =IF(E9=0,"",R9/E9) -> 1010.2112 | T9: =IF(E9=0,"",I9/E9) -> 1290.4632 | U9: =I9-R9 -> 102852.48 | V9: =IF(I9=0,"",(I9-K9-L9-M9-O9)/I9) -> 0.32255068 | W9: =IF(I9=0,"",U9/I9) -> 0.21717162
A10: VI O'Higgins | B10: PICHIDEGUA | C10: 225 | D10: 150 | E10: =C10+D10 -> 375 | F10: 400000 | G10: =F10*Parámetros!$B$12 -> 40000 | H10: 12000 | I10: 512000 | J10: =I10*(1+Parámetros!$B$10) -> 609280 | K10: =E10/Parámetros!$B$4*Parámetros!$B$5 -> 195000 | L10: =Parámetros!$B$6 -> 50000 | M10: 50000 | N10: =J10*Parámetros!$B$9 -> 18278.4 | O10: =Parámetros!$B$8 -> 30000 | P10: 1 | Q10: =IF(P10="",0,P10*Parámetros!$B$11) -> 33000 | R10: =K10+L10+M10+N10+O10+Q10 -> 376278.4 | S10: =IF(E10=0,"",R10/E10) -> 1003.4091 | T10: =IF(E10=0,"",I10/E10) -> 1365.3333 | U10: =I10-R10 -> 135721.6 | V10: =IF(I10=0,"",(I10-K10-L10-M10-O10)/I10) -> 0.36523438 | W10: =IF(I10=0,"",U10/I10) -> 0.26508125
A11: VI O'Higgins | B11: PEUMO | C11: 210 | D11: 158 | E11: =C11+D11 -> 368 | F11: 400000 | G11: =F11*Parámetros!$B$12 -> 40000 | H11: 12000 | I11: 512000 | J11: =I11*(1+Parámetros!$B$10) -> 609280 | K11: =E11/Parámetros!$B$4*Parámetros!$B$5 -> 191360 | L11: =Parámetros!$B$6 -> 50000 | M11: 50000 | N11: =J11*Parámetros!$B$9 -> 18278.4 | O11: =Parámetros!$B$8 -> 30000 | P11: 1 | Q11: =IF(P11="",0,P11*Parámetros!$B$11) -> 33000 | R11: =K11+L11+M11+N11+O11+Q11 -> 372638.4 | S11: =IF(E11=0,"",R11/E11) -> 1012.6043 | T11: =IF(E11=0,"",I11/E11) -> 1391.3043 | U11: =I11-R11 -> 139361.6 | V11: =IF(I11=0,"",(I11-K11-L11-M11-O11)/I11) -> 0.37234375 | W11: =IF(I11=0,"",U11/I11) -> 0.27219062
A12: VI O'Higgins | B12: REQUINOA | C12: 225 | D12: 171 | E12: =C12+D12 -> 396 | F12: 400000 | G12: =F12*Parámetros!$B$12 -> 40000 | H12: 12000 | I12: 512000 | J12: =I12*(1+Parámetros!$B$10) -> 609280 | K12: =E12/Parámetros!$B$4*Parámetros!$B$5 -> 205920 | L12: =Parámetros!$B$6 -> 50000 | M12: 50000 | N12: =J12*Parámetros!$B$9 -> 18278.4 | O12: =Parámetros!$B$8 -> 30000 | P12: 1 | Q12: =IF(P12="",0,P12*Parámetros!$B$11) -> 33000 | R12: =K12+L12+M12+N12+O12+Q12 -> 387198.4 | S12: =IF(E12=0,"",R12/E12) -> 977.77374 | T12: =IF(E12=0,"",I12/E12) -> 1292.9293 | U12: =I12-R12 -> 124801.6 | V12: =IF(I12=0,"",(I12-K12-L12-M12-O12)/I12) -> 0.34390625 | W12: =IF(I12=0,"",U12/I12) -> 0.24375312
A13: VI O'Higgins | B13: MARCHIGUE | C13: 265 | D13: 168 | E13: =C13+D13 -> 433 | F13: 400000 | G13: =F13*Parámetros!$B$12 -> 40000 | H13: 12000 | I13: 512000 | J13: =I13*(1+Parámetros!$B$10) -> 609280 | K13: =E13/Parámetros!$B$4*Parámetros!$B$5 -> 225160 | L13: =Parámetros!$B$6 -> 50000 | M13: 50000 | N13: =J13*Parámetros!$B$9 -> 18278.4 | O13: =Parámetros!$B$8 -> 30000 | P13: 1 | Q13: =IF(P13="",0,P13*Parámetros!$B$11) -> 33000 | R13: =K13+L13+M13+N13+O13+Q13 -> 406438.4 | S13: =IF(E13=0,"",R13/E13) -> 938.65681 | T13: =IF(E13=0,"",I13/E13) -> 1182.448 | U13: =I13-R13 -> 105561.6 | V13: =IF(I13=0,"",(I13-K13-L13-M13-O13)/I13) -> 0.30632813 | W13: =IF(I13=0,"",U13/I13) -> 0.206175
A14: VI O'Higgins | B14: PERALILLO | C14: 265 | D14: 168 | E14: =C14+D14 -> 433 | F14: 400000 | G14: =F14*Parámetros!$B$12 -> 40000 | H14: 12000 | I14: 512000 | J14: =I14*(1+Parámetros!$B$10) -> 609280 | K14: =E14/Parámetros!$B$4*Parámetros!$B$5 -> 225160 | L14: =Parámetros!$B$6 -> 50000 | M14: 50000 | N14: =J14*Parámetros!$B$9 -> 18278.4 | O14: =Parámetros!$B$8 -> 30000 | P14: 1 | Q14: =IF(P14="",0,P14*Parámetros!$B$11) -> 33000 | R14: =K14+L14+M14+N14+O14+Q14 -> 406438.4 | S14: =IF(E14=0,"",R14/E14) -> 938.65681 | T14: =IF(E14=0,"",I14/E14) -> 1182.448 | U14: =I14-R14 -> 105561.6 | V14: =IF(I14=0,"",(I14-K14-L14-M14-O14)/I14) -> 0.30632813 | W14: =IF(I14=0,"",U14/I14) -> 0.206175
A15: VI O'Higgins | B15: RENGO | C15: 240 | D15: 185 | E15: =C15+D15 -> 425 | F15: 410000 | G15: =F15*Parámetros!$B$12 -> 41000 | H15: 12000 | I15: 524800 | J15: =I15*(1+Parámetros!$B$10) -> 624512 | K15: =E15/Parámetros!$B$4*Parámetros!$B$5 -> 221000 | L15: =Parámetros!$B$6 -> 50000 | M15: 50000 | N15: =J15*Parámetros!$B$9 -> 18735.36 | O15: =Parámetros!$B$8 -> 30000 | P15: 1 | Q15: =IF(P15="",0,P15*Parámetros!$B$11) -> 33000 | R15: =K15+L15+M15+N15+O15+Q15 -> 402735.36 | S15: =IF(E15=0,"",R15/E15) -> 947.61261 | T15: =IF(E15=0,"",I15/E15) -> 1234.8235 | U15: =I15-R15 -> 122064.64 | V15: =IF(I15=0,"",(I15-K15-L15-M15-O15)/I15) -> 0.33117378 | W15: =IF(I15=0,"",U15/I15) -> 0.23259268
A16: VI O'Higgins | B16: SANTA CRUZ | C16: 263 | D16: 182 | E16: =C16+D16 -> 445 | F16: 410000 | G16: =F16*Parámetros!$B$12 -> 41000 | H16: 12000 | I16: 524800 | J16: =I16*(1+Parámetros!$B$10) -> 624512 | K16: =E16/Parámetros!$B$4*Parámetros!$B$5 -> 231400 | L16: =Parámetros!$B$6 -> 50000 | M16: 50000 | N16: =J16*Parámetros!$B$9 -> 18735.36 | O16: =Parámetros!$B$8 -> 30000 | P16: 1 | Q16: =IF(P16="",0,P16*Parámetros!$B$11) -> 33000 | R16: =K16+L16+M16+N16+O16+Q16 -> 413135.36 | S16: =IF(E16=0,"",R16/E16) -> 928.39407 | T16: =IF(E16=0,"",I16/E16) -> 1179.3258 | U16: =I16-R16 -> 111664.64 | V16: =IF(I16=0,"",(I16-K16-L16-M16-O16)/I16) -> 0.31135671 | W16: =IF(I16=0,"",U16/I16) -> 0.21277561
... A23: VI O'Higgins | B23: NANCAGUA | C23: 263 | D23: 224 | E23: =C23+D23 -> 487 | F23: 490000 | G23: =F23*Parámetros!$B$12 -> 49000 | H23: 12000 | I23: 627200 | J23: =I23*(1+Parámetros!$B$10) -> 746368 | K23: =E23/Parámetros!$B$4*Parámetros!$B$5 -> 253240 | L23: =Parámetros!$B$6 -> 50000 | M23: 50000 | N23: =J23*Parámetros!$B$9 -> 22391.04 | O23: =Parámetros!$B$8 -> 30000 | P23: 1 | Q23: =IF(P23="",0,P23*Parámetros!$B$11) -> 33000 | R23: =K23+L23+M23+N23+O23+Q23 -> 438631.04 | S23: =IF(E23=0,"",R23/E23) -> 900.67975 | T23: =IF(E23=0,"",I23/E23) -> 1287.885 | U23: =I23-R23 -> 188568.96 | V23: =IF(I23=0,"",(I23-K23-L23-M23-O23)/I23) -> 0.38896684 | W23: =IF(I23=0,"",U23/I23) -> 0.30065204

Sheet VII Maule
A1: REGIÓN DEL MAULE – Base Coltauco (vía Casablanca 188km)
A2: Verde=peaje real integrado | Naranja=tarifa nueva | Amarillo=input manual | Comisión=10% tarifa original
A3: Región | B3: Destino | C3: DISTANCIAS (km) | F3: Tarifa Original ($) | G3: Comisión Chofer 10% ($) | H3: Viatico Conductor | I3: Tarifa Nueva ($) | J3: Tarifa +IVA ($) | K3: Gasto Petróleo ($) | L3: Costos Fijos ($) | M3: Peajes I+V ($) | N3: Costo Financiero ($) | O3: Prov. Mant. ($) | P3: Días Chofer | Q3: Sueldo Base ($) | R3: Costo Total ($) | S3: Costo/km ($) | T3: Tarifa/km ($) | U3: Margen Op. ($) | V3: Margen Bruto % | W3: Margen Neto %
C4: Km Ida | D4: Km Vuelta | E4: Km Total
A5: VII Maule | B5: TENO | C5: 286 | D5: 248 | E5: =C5+D5 -> 534 | F5: 480000 | G5: =F5*Parámetros!$B$12 -> 48000 | H5: 12000 | I5: 614400 | J5: =I5*(1+Parámetros!$B$10) -> 731136 | K5: =E5/Parámetros!$B$4*Parámetros!$B$5 -> 277680 | L5: =Parámetros!$B$6 -> 50000 | N5: =J5*Parámetros!$B$9 -> 21934.08 | O5: =Parámetros!$B$8 -> 30000 | P5: 1 | Q5: =IF(P5="",0,P5*Parámetros!$B$11) -> 33000 | R5: =K5+L5+M5+N5+O5+Q5 -> 412614.08 | S5: =IF(E5=0,"",R5/E5) -> 772.68554 | T5: =IF(E5=0,"",I5/E5) -> 1150.5618 | U5: =I5-R5 -> 201785.92 | V5: =IF(I5=0,"",(I5-K5-L5-M5-O5)/I5) -> 0.41783854 | W5: =IF(I5=0,"",U5/I5) -> 0.3284276
A6: VII Maule | B6: CURICO | C6: 300 | D6: 262 | E6: =C6+D6 -> 562 | F6: 480000 | G6: =F6*Parámetros!$B$12 -> 48000 | H6: 12000 | I6: 614400 | J6: =I6*(1+Parámetros!$B$10) -> 731136 | K6: =E6/Parámetros!$B$4*Parámetros!$B$5 -> 292240 | L6: =Parámetros!$B$6 -> 50000 | N6: =J6*Parámetros!$B$9 -> 21934.08 | O6: =Parámetros!$B$8 -> 30000 | P6: 1 | Q6: =IF(P6="",0,P6*Parámetros!$B$11) -> 33000 | R6: =K6+L6+M6+N6+O6+Q6 -> 427174.08 | S6: =IF(E6=0,"",R6/E6) -> 760.09623 | T6: =IF(E6=0,"",I6/E6) -> 1093.2384 | U6: =I6-R6 -> 187225.92 | V6: =IF(I6=0,"",(I6-K6-L6-M6-O6)/I6) -> 0.39414063 | W6: =IF(I6=0,"",U6/I6) -> 0.30472969
A7: VII Maule | B7: ROMERAL | C7: 297 | D7: 259 | E7: =C7+D7 -> 556 | F7: 480000 | G7: =F7*Parámetros!$B$12 -> 48000 | H7: 12000 | I7: 614400 | J7: =I7*(1+Parámetros!$B$10) -> 731136 | K7: =E7/Parámetros!$B$4*Parámetros!$B$5 -> 289120 | L7: =Parámetros!$B$6 -> 50000 | N7: =J7*Parámetros!$B$9 -> 21934.08 | O7: =Parámetros!$B$8 -> 30000 | P7: 1 | Q7: =IF(P7="",0,P7*Parámetros!$B$11) -> 33000 | R7: =K7+L7+M7+N7+O7+Q7 -> 424054.08 | S7: =IF(E7=0,"",R7/E7) -> 762.68719 | T7: =IF(E7=0,"",I7/E7) -> 1105.036 | U7: =I7-R7 -> 190345.92 | V7: =IF(I7=0,"",(I7-K7-L7-M7-O7)/I7) -> 0.39921875 | W7: =IF(I7=0,"",U7/I7) -> 0.30980781
A8: VII Maule | B8: RAUCO | C8: 305 | D8: 267 | E8: =C8+D8 -> 572 | F8: 480000 | G8: =F8*Parámetros!$B$12 -> 48000 | H8: 12000 | I8: 614400 | J8: =I8*(1+Parámetros!$B$10) -> 731136 | K8: =E8/Parámetros!$B$4*Parámetros!$B$5 -> 297440 | L8: =Parámetros!$B$6 -> 50000 | N8: =J8*Parámetros!$B$9 -> 21934.08 | O8: =Parámetros!$B$8 -> 30000 | P8: 1 | Q8: =IF(P8="",0,P8*Parámetros!$B$11) -> 33000 | R8: =K8+L8+M8+N8+O8+Q8 -> 432374.08 | S8: =IF(E8=0,"",R8/E8) -> 755.89874 | T8: =IF(E8=0,"",I8/E8) -> 1074.1259 | U8: =I8-R8 -> 182025.92 | V8: =IF(I8=0,"",(I8-K8-L8-M8-O8)/I8) -> 0.38567708 | W8: =IF(I8=0,"",U8/I8) -> 0.29626615
A9: VII Maule | B9: MOLINA | C9: 317 | D9: 279 | E9: =C9+D9 -> 596 | F9: 480000 | G9: =F9*Parámetros!$B$12 -> 48000 | H9: 12000 | I9: 614400 | J9: =I9*(1+Parámetros!$B$10) -> 731136 | K9: =E9/Parámetros!$B$4*Parámetros!$B$5 -> 309920 | L9: =Parámetros!$B$6 -> 50000 | N9: =J9*Parámetros!$B$9 -> 21934.08 | O9: =Parámetros!$B$8 -> 30000 | P9: 1 | Q9: =IF(P9="",0,P9*Parámetros!$B$11) -> 33000 | R9: =K9+L9+M9+N9+O9+Q9 -> 444854.08 | S9: =IF(E9=0,"",R9/E9) -> 746.39946 | T9: =IF(E9=0,"",I9/E9) -> 1030.8725 | U9: =I9-R9 -> 169545.92 | V9: =IF(I9=0,"",(I9-K9-L9-M9-O9)/I9) -> 0.36536458 | W9: =IF(I9=0,"",U9/I9) -> 0.27595365
A10: VII Maule | B10: SAN RAFAEL | C10: 343 | D10: 305 | E10: =C10+D10 -> 648 | F10: 480000 | G10: =F10*Parámetros!$B$12 -> 48000 | H10: 12000 | I10: 614400 | J10: =I10*(1+Parámetros!$B$10) -> 731136 | K10: =E10/Parámetros!$B$4*Parámetros!$B$5 -> 336960 | L10: =Parámetros!$B$6 -> 50000 | N10: =J10*Parámetros!$B$9 -> 21934.08 | O10: =Parámetros!$B$8 -> 30000 | P10: 1 | Q10: =IF(P10="",0,P10*Parámetros!$B$11) -> 33000 | R10: =K10+L10+M10+N10+O10+Q10 -> 471894.08 | S10: =IF(E10=0,"",R10/E10) -> 728.2316 | T10: =IF(E10=0,"",I10/E10) -> 948.14815 | U10: =I10-R10 -> 142505.92 | V10: =IF(I10=0,"",(I10-K10-L10-M10-O10)/I10) -> 0.32135417 | W10: =IF(I10=0,"",U10/I10) -> 0.23194323
A11: VII Maule | B11: RIO CLARO | C11: 348 | D11: 310 | E11: =C11+D11 -> 658 | F11: 480000 | G11: =F11*Parámetros!$B$12 -> 48000 | H11: 12000 | I11: 614400 | J11: =I11*(1+Parámetros!$B$10) -> 731136 | K11: =E11/Parámetros!$B$4*Parámetros!$B$5 -> 342160 | L11: =Parámetros!$B$6 -> 50000 | N11: =J11*Parámetros!$B$9 -> 21934.08 | O11: =Parámetros!$B$8 -> 30000 | P11: 1 | Q11: =IF(P11="",0,P11*Parámetros!$B$11) -> 33000 | R11: =K11+L11+M11+N11+O11+Q11 -> 477094.08 | S11: =IF(E11=0,"",R11/E11) -> 725.06699 | T11: =IF(E11=0,"",I11/E11) -> 933.7386 | U11: =I11-R11 -> 137305.92 | V11: =IF(I11=0,"",(I11-K11-L11-M11-O11)/I11) -> 0.31289062 | W11: =IF(I11=0,"",U11/I11) -> 0.22347969
A12: VII Maule | B12: CUMPEO | C12: 348 | D12: 309 | E12: =C12+D12 -> 657 | F12: 480000 | G12: =F12*Parámetros!$B$12 -> 48000 | H12: 12000 | I12: 614400 | J12: =I12*(1+Parámetros!$B$10) -> 731136 | K12: =E12/Parámetros!$B$4*Parámetros!$B$5 -> 341640 | L12: =Parámetros!$B$6 -> 50000 | N12: =J12*Parámetros!$B$9 -> 21934.08 | O12: =Parámetros!$B$8 -> 30000 | P12: 1 | Q12: =IF(P12="",0,P12*Parámetros!$B$11) -> 33000 | R12: =K12+L12+M12+N12+O12+Q12 -> 476574.08 | S12: =IF(E12=0,"",R12/E12) -> 725.37912 | T12: =IF(E12=0,"",I12/E12) -> 935.15982 | U12: =I12-R12 -> 137825.92 | V12: =IF(I12=0,"",(I12-K12-L12-M12-O12)/I12) -> 0.31373698 | W12: =IF(I12=0,"",U12/I12) -> 0.22432604
A13: VII Maule | B13: TALCA | C13: 362 | D13: 324 | E13: =C13+D13 -> 686 | F13: 500000 | G13: =F13*Parámetros!$B$12 -> 50000 | H13: 12000 | I13: 640000 | J13: =I13*(1+Parámetros!$B$10) -> 761600 | K13: =E13/Parámetros!$B$4*Parámetros!$B$5 -> 356720 | L13: =Parámetros!$B$6 -> 50000 | N13: =J13*Parámetros!$B$9 -> 22848 | O13: =Parámetros!$B$8 -> 30000 | P13: 1 | Q13: =IF(P13="",0,P13*Parámetros!$B$11) -> 33000 | R13: =K13+L13+M13+N13+O13+Q13 -> 492568 | S13: =IF(E13=0,"",R13/E13) -> 718.02915 | T13: =IF(E13=0,"",I13/E13) -> 932.94461 | U13: =I13-R13 -> 147432 | V13: =IF(I13=0,"",(I13-K13-L13-M13-O13)/I13) -> 0.317625 | W13: =IF(I13=0,"",U13/I13) -> 0.2303625
A14: VII Maule | B14: HUALAÑE | C14: 377 | D14: 274 | E14: =C14+D14 -> 651 | F14: 500000 | G14: =F14*Parámetros!$B$12 -> 50000 | H14: 12000 | I14: 640000 | J14: =I14*(1+Parámetros!$B$10) -> 761600 | K14: =E14/Parámetros!$B$4*Parámetros!$B$5 -> 338520 | L14: =Parámetros!$B$6 -> 50000 | N14: =J14*Parámetros!$B$9 -> 22848 | O14: =Parámetros!$B$8 -> 30000 | P14: 1 | Q14: =IF(P14="",0,P14*Parámetros!$B$11) -> 33000 | R14: =K14+L14+M14+N14+O14+Q14 -> 474368 | S14: =IF(E14=0,"",R14/E14) -> 728.67588 | T14: =IF(E14=0,"",I14/E14) -> 983.10292 | U14: =I14-R14 -> 165632 | V14: =IF(I14=0,"",(I14-K14-L14-M14-O14)/I14) -> 0.3460625 | W14: =IF(I14=0,"",U14/I14) -> 0.2588
A15: VII Maule | B15: PENCAHUE | C15: 377 | D15: 339 | E15: =C15+D15 -> 716 | F15: 500000 | G15: =F15*Parámetros!$B$12 -> 50000 | H15: 12000 | I15: 640000 | J15: =I15*(1+Parámetros!$B$10) -> 761600 | K15: =E15/Parámetros!$B$4*Parámetros!$B$5 -> 372320 | L15: =Parámetros!$B$6 -> 50000 | N15: =J15*Parámetros!$B$9 -> 22848 | O15: =Parámetros!$B$8 -> 30000 | P15: 1 | Q15: =IF(P15="",0,P15*Parámetros!$B$11) -> 33000 | R15: =K15+L15+M15+N15+O15+Q15 -> 508168 | S15: =IF(E15=0,"",R15/E15) -> 709.73184 | T15: =IF(E15=0,"",I15/E15) -> 893.85475 | U15: =I15-R15 -> 131832 | V15: =IF(I15=0,"",(I15-K15-L15-M15-O15)/I15) -> 0.29325 | W15: =IF(I15=0,"",U15/I15) -> 0.2059875
A16: VII Maule | B16: SAN CLEMENTE | C16: 380 | D16: 342 | E16: =C16+D16 -> 722 | F16: 500000 | G16: =F16*Parámetros!$B$12 -> 50000 | H16: 12000 | I16: 640000 | J16: =I16*(1+Parámetros!$B$10) -> 761600 | K16: =E16/Parámetros!$B$4*Parámetros!$B$5 -> 375440 | L16: =Parámetros!$B$6 -> 50000 | N16: =J16*Parámetros!$B$9 -> 22848 | O16: =Parámetros!$B$8 -> 30000 | P16: 1 | Q16: =IF(P16="",0,P16*Parámetros!$B$11) -> 33000 | R16: =K16+L16+M16+N16+O16+Q16 -> 511288 | S16: =IF(E16=0,"",R16/E16) -> 708.15512 | T16: =IF(E16=0,"",I16/E16) -> 886.42659 | U16: =I16-R16 -> 128712 | V16: =IF(I16=0,"",(I16-K16-L16-M16-O16)/I16) -> 0.288375 | W16: =IF(I16=0,"",U16/I16) -> 0.2011125
... A24: VII Maule | B24: CAUQUENES | C24: 462 | D24: 423 | E24: =C24+D24 -> 885 | F24: 550000 | G24: =F24*Parámetros!$B$12 -> 55000 | H24: 12000 | I24: 704000 | J24: =I24*(1+Parámetros!$B$10) -> 837760 | K24: =E24/Parámetros!$B$4*Parámetros!$B$5 -> 460200 | L24: =Parámetros!$B$6 -> 50000 | N24: =J24*Parámetros!$B$9 -> 25132.8 | O24: =Parámetros!$B$8 -> 30000 | P24: 1 | Q24: =IF(P24="",0,P24*Parámetros!$B$11) -> 33000 | R24: =K24+L24+M24+N24+O24+Q24 -> 598332.8 | S24: =IF(E24=0,"",R24/E24) -> 676.08226 | T24: =IF(E24=0,"",I24/E24) -> 795.48023 | U24: =I24-R24 -> 105667.2 | V24: =IF(I24=0,"",(I24-K24-L24-M24-O24)/I24) -> 0.23267045 | W24: =IF(I24=0,"",U24/I24) -> 0.15009545

Sheet XVI Ñuble – VIII BioBío
A1: ÑUBLE Y BÍO BÍO – Base Coltauco (vía Casablanca 188km)
A2: Verde=peaje real integrado | Naranja=tarifa nueva | Amarillo=input manual | Comisión=10% tarifa original
A3: Región | B3: Destino | C3: DISTANCIAS (km) | F3: Tarifa Original ($) | G3: Comisión Chofer 10% ($) | H3: Viatico Conductor | I3: Tarifa Nueva ($) | J3: Tarifa +IVA ($) | K3: Gasto Petróleo ($) | L3: Costos Fijos ($) | M3: Peajes I+V ($) | N3: Costo Financiero ($) | O3: Prov. Mant. ($) | P3: Días Chofer | Q3: Sueldo Base ($) | R3: Costo Total ($) | S3: Costo/km ($) | T3: Tarifa/km ($) | U3: Margen Op. ($) | V3: Margen Bruto % | W3: Margen Neto %
C4: Km Ida | D4: Km Vuelta | E4: Km Total
A5: Ñuble/BioBío | B5: SAN CARLOS | C5: 486 | D5: 448 | E5: =C5+D5 -> 934 | F5: 600000 | G5: =F5*Parámetros!$B$12 -> 60000 | H5: 12000 | I5: 750000 | J5: =I5*(1+Parámetros!$B$10) -> 892500 | K5: =E5/Parámetros!$B$4*Parámetros!$B$5 -> 485680 | L5: =Parámetros!$B$6 -> 50000 | N5: =J5*Parámetros!$B$9 -> 26775 | O5: =Parámetros!$B$8 -> 30000 | P5: 2 | Q5: =IF(P5="",0,P5*Parámetros!$B$11) -> 66000 | R5: =K5+L5+M5+N5+O5+Q5 -> 658455 | S5: =IF(E5=0,"",R5/E5) -> 704.98394 | T5: =IF(E5=0,"",I5/E5) -> 802.99786 | U5: =I5-R5 -> 91545 | V5: =IF(I5=0,"",(I5-K5-L5-M5-O5)/I5) -> 0.24576 | W5: =IF(I5=0,"",U5/I5) -> 0.12206
A6: Ñuble/BioBío | B6: CHILLAN | C6: 510 | D6: 472 | E6: =C6+D6 -> 982 | F6: 650000 | G6: =F6*Parámetros!$B$12 -> 65000 | H6: 12000 | I6: 812500 | J6: =I6*(1+Parámetros!$B$10) -> 966875 | K6: =E6/Parámetros!$B$4*Parámetros!$B$5 -> 510640 | L6: =Parámetros!$B$6 -> 50000 | N6: =J6*Parámetros!$B$9 -> 29006.25 | O6: =Parámetros!$B$8 -> 30000 | P6: 2 | Q6: =IF(P6="",0,P6*Parámetros!$B$11) -> 66000 | R6: =K6+L6+M6+N6+O6+Q6 -> 685646.25 | S6: =IF(E6=0,"",R6/E6) -> 698.2141 | T6: =IF(E6=0,"",I6/E6) -> 827.39308 | U6: =I6-R6 -> 126853.75 | V6: =IF(I6=0,"",(I6-K6-L6-M6-O6)/I6) -> 0.27305846 | W6: =IF(I6=0,"",U6/I6) -> 0.15612769
A7: Ñuble/BioBío | B7: SAN NICOLAS | C7: 515 | D7: 477 | E7: =C7+D7 -> 992 | F7: 650000 | G7: =F7*Parámetros!$B$12 -> 65000 | H7: 12000 | I7: 812500 | J7: =I7*(1+Parámetros!$B$10) -> 966875 | K7: =E7/Parámetros!$B$4*Parámetros!$B$5 -> 515840 | L7: =Parámetros!$B$6 -> 50000 | N7: =J7*Parámetros!$B$9 -> 29006.25 | O7: =Parámetros!$B$8 -> 30000 | P7: 2 | Q7: =IF(P7="",0,P7*Parámetros!$B$11) -> 66000 | R7: =K7+L7+M7+N7+O7+Q7 -> 690846.25 | S7: =IF(E7=0,"",R7/E7) -> 696.41759 | T7: =IF(E7=0,"",I7/E7) -> 819.05242 | U7: =I7-R7 -> 121653.75 | V7: =IF(I7=0,"",(I7-K7-L7-M7-O7)/I7) -> 0.26665846 | W7: =IF(I7=0,"",U7/I7) -> 0.14972769
A8: Ñuble/BioBío | B8: SAN IGNACIO | C8: 515 | D8: 477 | E8: =C8+D8 -> 992 | F8: 670000 | G8: =F8*Parámetros!$B$12 -> 67000 | H8: 12000 | I8: 837500 | J8: =I8*(1+Parámetros!$B$10) -> 996625 | K8: =E8/Parámetros!$B$4*Parámetros!$B$5 -> 515840 | L8: =Parámetros!$B$6 -> 50000 | N8: =J8*Parámetros!$B$9 -> 29898.75 | O8: =Parámetros!$B$8 -> 30000 | P8: 2 | Q8: =IF(P8="",0,P8*Parámetros!$B$11) -> 66000 | R8: =K8+L8+M8+N8+O8+Q8 -> 691738.75 | S8: =IF(E8=0,"",R8/E8) -> 697.31729 | T8: =IF(E8=0,"",I8/E8) -> 844.25403 | U8: =I8-R8 -> 145761.25 | V8: =IF(I8=0,"",(I8-K8-L8-M8-O8)/I8) -> 0.28854925 | W8: =IF(I8=0,"",U8/I8) -> 0.17404328
A9: Ñuble/BioBío | B9: COIHUECO | C9: 532 | D9: 494 | E9: =C9+D9 -> 1026 | F9: 670000 | G9: =F9*Parámetros!$B$12 -> 67000 | H9: 12000 | I9: 837500 | J9: =I9*(1+Parámetros!$B$10) -> 996625 | K9: =E9/Parámetros!$B$4*Parámetros!$B$5 -> 533520 | L9: =Parámetros!$B$6 -> 50000 | N9: =J9*Parámetros!$B$9 -> 29898.75 | O9: =Parámetros!$B$8 -> 30000 | P9: 2 | Q9: =IF(P9="",0,P9*Parámetros!$B$11) -> 66000 | R9: =K9+L9+M9+N9+O9+Q9 -> 709418.75 | S9: =IF(E9=0,"",R9/E9) -> 691.44128 | T9: =IF(E9=0,"",I9/E9) -> 816.2768 | U9: =I9-R9 -> 128081.25 | V9: =IF(I9=0,"",(I9-K9-L9-M9-O9)/I9) -> 0.26743881 | W9: =IF(I9=0,"",U9/I9) -> 0.15293284
A10: Ñuble/BioBío | B10: BULNES | C10: 534 | D10: 496 | E10: =C10+D10 -> 1030 | F10: 670000 | G10: =F10*Parámetros!$B$12 -> 67000 | H10: 12000 | I10: 837500 | J10: =I10*(1+Parámetros!$B$10) -> 996625 | K10: =E10/Parámetros!$B$4*Parámetros!$B$5 -> 535600 | L10: =Parámetros!$B$6 -> 50000 | N10: =J10*Parámetros!$B$9 -> 29898.75 | O10: =Parámetros!$B$8 -> 30000 | P10: 2 | Q10: =IF(P10="",0,P10*Parámetros!$B$11) -> 66000 | R10: =K10+L10+M10+N10+O10+Q10 -> 711498.75 | S10: =IF(E10=0,"",R10/E10) -> 690.77549 | T10: =IF(E10=0,"",I10/E10) -> 813.1068 | U10: =I10-R10 -> 126001.25 | V10: =IF(I10=0,"",(I10-K10-L10-M10-O10)/I10) -> 0.26495522 | W10: =IF(I10=0,"",U10/I10) -> 0.15044925
A11: Ñuble/BioBío | B11: EL CARMEN | C11: 556 | D11: 518 | E11: =C11+D11 -> 1074 | F11: 690000 | G11: =F11*Parámetros!$B$12 -> 69000 | H11: 12000 | I11: 862500 | J11: =I11*(1+Parámetros!$B$10) -> 1026375 | K11: =E11/Parámetros!$B$4*Parámetros!$B$5 -> 558480 | L11: =Parámetros!$B$6 -> 50000 | N11: =J11*Parámetros!$B$9 -> 30791.25 | O11: =Parámetros!$B$8 -> 30000 | P11: 2 | Q11: =IF(P11="",0,P11*Parámetros!$B$11) -> 66000 | R11: =K11+L11+M11+N11+O11+Q11 -> 735271.25 | S11: =IF(E11=0,"",R11/E11) -> 684.6101 | T11: =IF(E11=0,"",I11/E11) -> 803.07263 | U11: =I11-R11 -> 127228.75 | V11: =IF(I11=0,"",(I11-K11-L11-M11-O11)/I11) -> 0.25973333 | W11: =IF(I11=0,"",U11/I11) -> 0.14751159
A12: Ñuble/BioBío | B12: PEMUCO | C12: 580 | D12: 542 | E12: =C12+D12 -> 1122 | F12: 720000 | G12: =F12*Parámetros!$B$12 -> 72000 | H12: 12000 | I12: 900000 | J12: =I12*(1+Parámetros!$B$10) -> 1071000 | K12: =E12/Parámetros!$B$4*Parámetros!$B$5 -> 583440 | L12: =Parámetros!$B$6 -> 50000 | N12: =J12*Parámetros!$B$9 -> 32130 | O12: =Parámetros!$B$8 -> 30000 | P12: 2 | Q12: =IF(P12="",0,P12*Parámetros!$B$11) -> 66000 | R12: =K12+L12+M12+N12+O12+Q12 -> 761570 | S12: =IF(E12=0,"",R12/E12) -> 678.76114 | T12: =IF(E12=0,"",I12/E12) -> 802.13904 | U12: =I12-R12 -> 138430 | V12: =IF(I12=0,"",(I12-K12-L12-M12-O12)/I12) -> 0.26284444 | W12: =IF(I12=0,"",U12/I12) -> 0.15381111
A13: Ñuble/BioBío | B13: YUNGAY | C13: 607 | D13: 568 | E13: =C13+D13 -> 1175 | F13: 750000 | G13: =F13*Parámetros!$B$12 -> 75000 | H13: 12000 | I13: 937500 | J13: =I13*(1+Parámetros!$B$10) -> 1115625 | K13: =E13/Parámetros!$B$4*Parámetros!$B$5 -> 611000 | L13: =Parámetros!$B$6 -> 50000 | N13: =J13*Parámetros!$B$9 -> 33468.75 | O13: =Parámetros!$B$8 -> 30000 | P13: 2 | Q13: =IF(P13="",0,P13*Parámetros!$B$11) -> 66000 | R13: =K13+L13+M13+N13+O13+Q13 -> 790468.75 | S13: =IF(E13=0,"",R13/E13) -> 672.73936 | T13: =IF(E13=0,"",I13/E13) -> 797.87234 | U13: =I13-R13 -> 147031.25 | V13: =IF(I13=0,"",(I13-K13-L13-M13-O13)/I13) -> 0.26293333 | W13: =IF(I13=0,"",U13/I13) -> 0.15683333
A14: Ñuble/BioBío | B14: YUMBEL | C14: 592 | D14: 554 | E14: =C14+D14 -> 1146 | F14: 720000 | G14: =F14*Parámetros!$B$12 -> 72000 | H14: 12000 | I14: 900000 | J14: =I14*(1+Parámetros!$B$10) -> 1071000 | K14: =E14/Parámetros!$B$4*Parámetros!$B$5 -> 595920 | L14: =Parámetros!$B$6 -> 50000 | N14: =J14*Parámetros!$B$9 -> 32130 | O14: =Parámetros!$B$8 -> 30000 | P14: 2 | Q14: =IF(P14="",0,P14*Parámetros!$B$11) -> 66000 | R14: =K14+L14+M14+N14+O14+Q14 -> 774050 | S14: =IF(E14=0,"",R14/E14) -> 675.4363 | T14: =IF(E14=0,"",I14/E14) -> 785.34031 | U14: =I14-R14 -> 125950 | V14: =IF(I14=0,"",(I14-K14-L14-M14-O14)/I14) -> 0.24897778 | W14: =IF(I14=0,"",U14/I14) -> 0.13994444
A15: Ñuble/BioBío | B15: PENCO | C15: 599 | D15: 561 | E15: =C15+D15 -> 1160 | F15: 750000 | G15: =F15*Parámetros!$B$12 -> 75000 | H15: 12000 | I15: 937500 | J15: =I15*(1+Parámetros!$B$10) -> 1115625 | K15: =E15/Parámetros!$B$4*Parámetros!$B$5 -> 603200 | L15: =Parámetros!$B$6 -> 50000 | N15: =J15*Parámetros!$B$9 -> 33468.75 | O15: =Parámetros!$B$8 -> 30000 | P15: 2 | Q15: =IF(P15="",0,P15*Parámetros!$B$11) -> 66000 | R15: =K15+L15+M15+N15+O15+Q15 -> 782668.75 | S15: =IF(E15=0,"",R15/E15) -> 674.71444 | T15: =IF(E15=0,"",I15/E15) -> 808.18966 | U15: =I15-R15 -> 154831.25 | V15: =IF(I15=0,"",(I15-K15-L15-M15-O15)/I15) -> 0.27125333 | W15: =IF(I15=0,"",U15/I15) -> 0.16515333
A16: Ñuble/BioBío | B16: CONCEPCION | C16: 606 | D16: 568 | E16: =C16+D16 -> 1174 | F16: 750000 | G16: =F16*Parámetros!$B$12 -> 75000 | H16: 12000 | I16: 937500 | J16: =I16*(1+Parámetros!$B$10) -> 1115625 | K16: =E16/Parámetros!$B$4*Parámetros!$B$5 -> 610480 | L16: =Parámetros!$B$6 -> 50000 | N16: =J16*Parámetros!$B$9 -> 33468.75 | O16: =Parámetros!$B$8 -> 30000 | P16: 2 | Q16: =IF(P16="",0,P16*Parámetros!$B$11) -> 66000 | R16: =K16+L16+M16+N16+O16+Q16 -> 789948.75 | S16: =IF(E16=0,"",R16/E16) -> 672.86946 | T16: =IF(E16=0,"",I16/E16) -> 798.55196 | U16: =I16-R16 -> 147551.25 | V16: =IF(I16=0,"",(I16-K16-L16-M16-O16)/I16) -> 0.263488 | W16: =IF(I16=0,"",U16/I16) -> 0.157388
... A24: Ñuble/BioBío | B24: CAÑETE | C24: 774 | D24: 703 | E24: =C24+D24 -> 1477 | F24: 950000 | G24: =F24*Parámetros!$B$12 -> 95000 | H24: 12000 | I24: 1187500 | J24: =I24*(1+Parámetros!$B$10) -> 1413125 | K24: =E24/Parámetros!$B$4*Parámetros!$B$5 -> 768040 | L24: =Parámetros!$B$6 -> 50000 | N24: =J24*Parámetros!$B$9 -> 42393.75 | O24: =Parámetros!$B$8 -> 30000 | P24: 2 | Q24: =IF(P24="",0,P24*Parámetros!$B$11) -> 66000 | R24: =K24+L24+M24+N24+O24+Q24 -> 956433.75 | S24: =IF(E24=0,"",R24/E24) -> 647.55162 | T24: =IF(E24=0,"",I24/E24) -> 803.99458 | U24: =I24-R24 -> 231066.25 | V24: =IF(I24=0,"",(I24-K24-L24-M24-O24)/I24) -> 0.28586105 | W24: =IF(I24=0,"",U24/I24) -> 0.19458211

Sheet CONSOLIDADO
A1: CONSOLIDADO TODAS LAS REGIONES – GLOBAL SOLUTIONS SpA
A2: Verde=peaje real integrado | Naranja=tarifa nueva | Amarillo=input manual | Comisión=10% tarifa original
A3: Región | B3: Destino | C3: DISTANCIAS (km) | F3: Tarifa Original ($) | G3: Comisión Chofer 10% ($) | H3: Viatico Conductor | I3: Tarifa Nueva ($) | J3: Tarifa +IVA ($) | K3: Gasto Petróleo ($) | L3: Costos Fijos ($) | M3: Peajes I+V ($) | N3: Costo Financiero ($) | O3: Prov. Mant. ($) | P3: Días Chofer | Q3: Sueldo Base ($) | R3: Costo Total ($) | S3: Costo/km ($) | T3: Tarifa/km ($) | U3: Margen Op. ($) | V3: Margen Bruto % | W3: Margen Neto %
C4: Km Ida | D4: Km Vuelta | E4: Km Total
A5: RM | B5: ALHUE | C5: 75 | D5: 75 | E5: =C5+D5 -> 150 | F5: 300000 | G5: =F5*Parámetros!$B$12 -> 30000 | H5: 12000 | I5: 354000 | J5: =I5*(1+Parámetros!$B$10) -> 421260 | K5: =E5/Parámetros!$B$4*Parámetros!$B$5 -> 78000 | L5: =Parámetros!$B$6 -> 50000 | M5: 0 | N5: =J5*Parámetros!$B$9 -> 12637.8 | O5: =Parámetros!$B$8 -> 30000 | Q5: =IF(P5="",0,P5*Parámetros!$B$11) -> 0 | R5: =K5+L5+M5+N5+O5+Q5 -> 170637.8 | S5: =IF(E5=0,"",R5/E5) -> 1137.5853 | T5: =IF(E5=0,"",I5/E5) -> 2360 | U5: =I5-R5 -> 183362.2 | V5: =IF(I5=0,"",(I5-K5-L5-M5-O5)/I5) -> 0.55367232 | W5: =IF(I5=0,"",U5/I5) -> 0.51797232
A6: RM | B6: BUIN | C6: 88 | D6: 88 | E6: =C6+D6 -> 176 | F6: 300000 | G6: =F6*Parámetros!$B$12 -> 30000 | H6: 12000 | I6: 354000 | J6: =I6*(1+Parámetros!$B$10) -> 421260 | K6: =E6/Parámetros!$B$4*Parámetros!$B$5 -> 91520 | L6: =Parámetros!$B$6 -> 50000 | M6: 39800 | N6: =J6*Parámetros!$B$9 -> 12637.8 | O6: =Parámetros!$B$8 -> 30000 | Q6: =IF(P6="",0,P6*Parámetros!$B$11) -> 0 | R6: =K6+L6+M6+N6+O6+Q6 -> 223957.8 | S6: =IF(E6=0,"",R6/E6) -> 1272.4875 | T6: =IF(E6=0,"",I6/E6) -> 2011.3636 | U6: =I6-R6 -> 130042.2 | V6: =IF(I6=0,"",(I6-K6-L6-M6-O6)/I6) -> 0.40305085 | W6: =IF(I6=0,"",U6/I6) -> 0.36735085
A7: RM | B7: COLINA | C7: 93 | D7: 93 | E7: =C7+D7 -> 186 | F7: 300000 | G7: =F7*Parámetros!$B$12 -> 30000 | H7: 12000 | I7: 354000 | J7: =I7*(1+Parámetros!$B$10) -> 421260 | K7: =E7/Parámetros!$B$4*Parámetros!$B$5 -> 96720 | L7: =Parámetros!$B$6 -> 50000 | M7: 33200 | N7: =J7*Parámetros!$B$9 -> 12637.8 | O7: =Parámetros!$B$8 -> 30000 | Q7: =IF(P7="",0,P7*Parámetros!$B$11) -> 0 | R7: =K7+L7+M7+N7+O7+Q7 -> 222557.8 | S7: =IF(E7=0,"",R7/E7) -> 1196.5473 | T7: =IF(E7=0,"",I7/E7) -> 1903.2258 | U7: =I7-R7 -> 131442.2 | V7: =IF(I7=0,"",(I7-K7-L7-M7-O7)/I7) -> 0.40700565 | W7: =IF(I7=0,"",U7/I7) -> 0.37130565
A8: RM | B8: CURACAVI | C8: 34 | D8: 34 | E8: =C8+D8 -> 68 | F8: 280000 | G8: =F8*Parámetros!$B$12 -> 28000 | H8: 12000 | I8: 330400 | J8: =I8*(1+Parámetros!$B$10) -> 393176 | K8: =E8/Parámetros!$B$4*Parámetros!$B$5 -> 35360 | L8: =Parámetros!$B$6 -> 50000 | M8: 0 | N8: =J8*Parámetros!$B$9 -> 11795.28 | O8: =Parámetros!$B$8 -> 30000 | Q8: =IF(P8="",0,P8*Parámetros!$B$11) -> 0 | R8: =K8+L8+M8+N8+O8+Q8 -> 127155.28 | S8: =IF(E8=0,"",R8/E8) -> 1869.9306 | T8: =IF(E8=0,"",I8/E8) -> 4858.8235 | U8: =I8-R8 -> 203244.72 | V8: =IF(I8=0,"",(I8-K8-L8-M8-O8)/I8) -> 0.65084746 | W8: =IF(I8=0,"",U8/I8) -> 0.61514746
A9: RM | B9: EL MONTE | C9: 75 | D9: 75 | E9: =C9+D9 -> 150 | F9: 300000 | G9: =F9*Parámetros!$B$12 -> 30000 | H9: 12000 | I9: 354000 | J9: =I9*(1+Parámetros!$B$10) -> 421260 | K9: =E9/Parámetros!$B$4*Parámetros!$B$5 -> 78000 | L9: =Parámetros!$B$6 -> 50000 | M9: 33200 | N9: =J9*Parámetros!$B$9 -> 12637.8 | O9: =Parámetros!$B$8 -> 30000 | Q9: =IF(P9="",0,P9*Parámetros!$B$11) -> 0 | R9: =K9+L9+M9+N9+O9+Q9 -> 203837.8 | S9: =IF(E9=0,"",R9/E9) -> 1358.9187 | T9: =IF(E9=0,"",I9/E9) -> 2360 | U9: =I9-R9 -> 150162.2 | V9: =IF(I9=0,"",(I9-K9-L9-M9-O9)/I9) -> 0.45988701 | W9: =IF(I9=0,"",U9/I9) -> 0.42418701
A10: RM | B10: ISLA MAIPO | C10: 75 | D10: 75 | E10: =C10+D10 -> 150 | F10: 300000 | G10: =F10*Parámetros!$B$12 -> 30000 | H10: 12000 | I10: 354000 | J10: =I10*(1+Parámetros!$B$10) -> 421260 | K10: =E10/Parámetros!$B$4*Parámetros!$B$5 -> 78000 | L10: =Parámetros!$B$6 -> 50000 | M10: 33200 | N10: =J10*Parámetros!$B$9 -> 12637.8 | O10: =Parámetros!$B$8 -> 30000 | Q10: =IF(P10="",0,P10*Parámetros!$B$11) -> 0 | R10: =K10+L10+M10+N10+O10+Q10 -> 203837.8 | S10: =IF(E10=0,"",R10/E10) -> 1358.9187 | T10: =IF(E10=0,"",I10/E10) -> 2360 | U10: =I10-R10 -> 150162.2 | V10: =IF(I10=0,"",(I10-K10-L10-M10-O10)/I10) -> 0.45988701 | W10: =IF(I10=0,"",U10/I10) -> 0.42418701
A11: RM | B11: LAMPA | C11: 93 | D11: 93 | E11: =C11+D11 -> 186 | F11: 280000 | G11: =F11*Parámetros!$B$12 -> 28000 | H11: 12000 | I11: 330400 | J11: =I11*(1+Parámetros!$B$10) -> 393176 | K11: =E11/Parámetros!$B$4*Parámetros!$B$5 -> 96720 | L11: =Parámetros!$B$6 -> 50000 | M11: 33200 | N11: =J11*Parámetros!$B$9 -> 11795.28 | O11: =Parámetros!$B$8 -> 30000 | Q11: =IF(P11="",0,P11*Parámetros!$B$11) -> 0 | R11: =K11+L11+M11+N11+O11+Q11 -> 221715.28 | S11: =IF(E11=0,"",R11/E11) -> 1192.0176 | T11: =IF(E11=0,"",I11/E11) -> 1776.3441 | U11: =I11-R11 -> 108684.72 | V11: =IF(I11=0,"",(I11-K11-L11-M11-O11)/I11) -> 0.36464891 | W11: =IF(I11=0,"",U11/I11) -> 0.32894891
A12: RM | B12: MARIA PINTO | C12: 56 | D12: 56 | E12: =C12+D12 -> 112 | F12: 280000 | G12: =F12*Parámetros!$B$12 -> 28000 | H12: 12000 | I12: 330400 | J12: =I12*(1+Parámetros!$B$10) -> 393176 | K12: =E12/Parámetros!$B$4*Parámetros!$B$5 -> 58240 | L12: =Parámetros!$B$6 -> 50000 | M12: 0 | N12: =J12*Parámetros!$B$9 -> 11795.28 | O12: =Parámetros!$B$8 -> 30000 | Q12: =IF(P12="",0,P12*Parámetros!$B$11) -> 0 | R12: =K12+L12+M12+N12+O12+Q12 -> 150035.28 | S12: =IF(E12=0,"",R12/E12) -> 1339.6007 | T12: =IF(E12=0,"",I12/E12) -> 2950 | U12: =I12-R12 -> 180364.72 | V12: =IF(I12=0,"",(I12-K12-L12-M12-O12)/I12) -> 0.58159806 | W12: =IF(I12=0,"",U12/I12) -> 0.54589806
A13: RM | B13: PAINE | C13: 88 | D13: 88 | E13: =C13+D13 -> 176 | F13: 300000 | G13: =F13*Parámetros!$B$12 -> 30000 | H13: 12000 | I13: 354000 | J13: =I13*(1+Parámetros!$B$10) -> 421260 | K13: =E13/Parámetros!$B$4*Parámetros!$B$5 -> 91520 | L13: =Parámetros!$B$6 -> 50000 | M13: 39800 | N13: =J13*Parámetros!$B$9 -> 12637.8 | O13: =Parámetros!$B$8 -> 30000 | Q13: =IF(P13="",0,P13*Parámetros!$B$11) -> 0 | R13: =K13+L13+M13+N13+O13+Q13 -> 223957.8 | S13: =IF(E13=0,"",R13/E13) -> 1272.4875 | T13: =IF(E13=0,"",I13/E13) -> 2011.3636 | U13: =I13-R13 -> 130042.2 | V13: =IF(I13=0,"",(I13-K13-L13-M13-O13)/I13) -> 0.40305085 | W13: =IF(I13=0,"",U13/I13) -> 0.36735085
A14: RM | B14: PEÑAFLOR | C14: 75 | D14: 75 | E14: =C14+D14 -> 150 | F14: 300000 | G14: =F14*Parámetros!$B$12 -> 30000 | H14: 12000 | I14: 354000 | J14: =I14*(1+Parámetros!$B$10) -> 421260 | K14: =E14/Parámetros!$B$4*Parámetros!$B$5 -> 78000 | L14: =Parámetros!$B$6 -> 50000 | M14: 33200 | N14: =J14*Parámetros!$B$9 -> 12637.8 | O14: =Parámetros!$B$8 -> 30000 | Q14: =IF(P14="",0,P14*Parámetros!$B$11) -> 0 | R14: =K14+L14+M14+N14+O14+Q14 -> 203837.8 | S14: =IF(E14=0,"",R14/E14) -> 1358.9187 | T14: =IF(E14=0,"",I14/E14) -> 2360 | U14: =I14-R14 -> 150162.2 | V14: =IF(I14=0,"",(I14-K14-L14-M14-O14)/I14) -> 0.45988701 | W14: =IF(I14=0,"",U14/I14) -> 0.42418701
A15: RM | B15: POMAIRE | C15: 87 | D15: 87 | E15: =C15+D15 -> 174 | F15: 280000 | G15: =F15*Parámetros!$B$12 -> 28000 | H15: 12000 | I15: 330400 | J15: =I15*(1+Parámetros!$B$10) -> 393176 | K15: =E15/Parámetros!$B$4*Parámetros!$B$5 -> 90480 | L15: =Parámetros!$B$6 -> 50000 | M15: 0 | N15: =J15*Parámetros!$B$9 -> 11795.28 | O15: =Parámetros!$B$8 -> 30000 | Q15: =IF(P15="",0,P15*Parámetros!$B$11) -> 0 | R15: =K15+L15+M15+N15+O15+Q15 -> 182275.28 | S15: =IF(E15=0,"",R15/E15) -> 1047.5591 | T15: =IF(E15=0,"",I15/E15) -> 1898.8506 | U15: =I15-R15 -> 148124.72 | V15: =IF(I15=0,"",(I15-K15-L15-M15-O15)/I15) -> 0.48401937 | W15: =IF(I15=0,"",U15/I15) -> 0.44831937
A16: RM | B16: SAN BERNARDO | C16: 88 | D16: 88 | E16: =C16+D16 -> 176 | F16: 300000 | G16: =F16*Parámetros!$B$12 -> 30000 | H16: 12000 | I16: 354000 | J16: =I16*(1+Parámetros!$B$10) -> 421260 | K16: =E16/Parámetros!$B$4*Parámetros!$B$5 -> 91520 | L16: =Parámetros!$B$6 -> 50000 | M16: 39800 | N16: =J16*Parámetros!$B$9 -> 12637.8 | O16: =Parámetros!$B$8 -> 30000 | Q16: =IF(P16="",0,P16*Parámetros!$B$11) -> 0 | R16: =K16+L16+M16+N16+O16+Q16 -> 223957.8 | S16: =IF(E16=0,"",R16/E16) -> 1272.4875 | T16: =IF(E16=0,"",I16/E16) -> 2011.3636 | U16: =I16-R16 -> 130042.2 | V16: =IF(I16=0,"",(I16-K16-L16-M16-O16)/I16) -> 0.40305085 | W16: =IF(I16=0,"",U16/I16) -> 0.36735085
... A95: Ñuble/BioBío | B95: CAÑETE | C95: 774 | D95: 703 | E95: =C95+D95 -> 1477 | F95: 950000 | G95: =F95*Parámetros!$B$12 -> 95000 | H95: 12000 | I95: 1187500 | J95: =I95*(1+Parámetros!$B$10) -> 1413125 | K95: =E95/Parámetros!$B$4*Parámetros!$B$5 -> 768040 | L95: =Parámetros!$B$6 -> 50000 | M95: 155600 | N95: =J95*Parámetros!$B$9 -> 42393.75 | O95: =Parámetros!$B$8 -> 30000 | Q95: =IF(P95="",0,P95*Parámetros!$B$11) -> 0 | R95: =K95+L95+M95+N95+O95+Q95 -> 1046033.7 | S95: =IF(E95=0,"",R95/E95) -> 708.21513 | T95: =IF(E95=0,"",I95/E95) -> 803.99458 | U95: =I95-R95 -> 141466.25 | V95: =IF(I95=0,"",(I95-K95-L95-M95-O95)/I95) -> 0.15482947 | W95: =IF(I95=0,"",U95/I95) -> 0.11912947
