Workbook

Sheet Supuestos
A1: SUPUESTOS
A2: Supuesto | B2: Valor
A3: Rendimiento (km/L) | B3: 3
A4: Precio litro ($) | B4: 1200
A5: Mantención programada ($/km) | B5: 26.67
A6: Provisión reparaciones ($/día de uso) | B6: 25000
A7: Sueldo chofer ($/día) | B7: 33000
A8: Viático ($/día) | B8: 12000
A9: Costo fijo equipo ($/día) | B9: 36000
A10: Comisión chofer (% tarifa neta) | B10: 0.08
A11: Factoring (% facturado bruto) | B11: 0.015
A12: % Retorno sobre tarifa base | B12: 0.6
A13: Peaje sur corto (<162km desde PH) | B13: 28372
A14: Peaje sur largo (>162km desde PH) | B14: 52772
... A16: % Ajuste Tarifas (+sube / -baja todas las tarifas) | B16: 0

Sheet T1_Locales
A1: Origen | B1: Local | C1: Tarifa | D1: Km | E1: Peaje | F1: Clave
A2: Padre Hurtado | B2: Quilicura | C2: 124107 | D2: 40 | E2: 10000 | F2: =A2&B2 -> Padre HurtadoQuilicura
A3: Padre Hurtado | B3: Melipilla | C3: 124107 | D3: 50 | E3: 13000 | F3: =A3&B3 -> Padre HurtadoMelipilla
A4: Padre Hurtado | B4: Lampa | C4: 124107 | D4: 46 | E4: 13000 | F4: =A4&B4 -> Padre HurtadoLampa
A5: Padre Hurtado | B5: San Felipe | C5: 213845 | D5: 133 | E5: 24600 | F5: =A5&B5 -> Padre HurtadoSan Felipe
A6: San Bernardo | B6: Quilicura | C6: 158236 | D6: 31 | E6: 10000 | F6: =A6&B6 -> San BernardoQuilicura
A7: San Bernardo | B7: Melipilla | C7: 158236 | D7: 60 | E7: 13000 | F7: =A7&B7 -> San BernardoMelipilla
A8: San Bernardo | B8: Lampa | C8: 158236 | D8: 48 | E8: 13000 | F8: =A8&B8 -> San BernardoLampa
A9: San Bernardo | B9: San Felipe | C9: 240098 | D9: 107 | E9: 24600 | F9: =A9&B9 -> San BernardoSan Felipe
A10: Loginsa | B10: Quilicura | C10: 143964 | D10: 22 | E10: 10000 | F10: =A10&B10 -> LoginsaQuilicura
A11: Loginsa | B11: Melipilla | C11: 143964 | D11: 60 | E11: 13000 | F11: =A11&B11 -> LoginsaMelipilla
A12: Loginsa | B12: Lampa | C12: 143964 | D12: 36 | E12: 13000 | F12: =A12&B12 -> LoginsaLampa
A13: Loginsa | B13: San Felipe | C13: 229120 | D13: 100 | E13: 24600 | F13: =A13&B13 -> LoginsaSan Felipe
... A104: Llay Llay | B104: San Felipe | C104: 152746 | D104: 20 | E104: 0 | F104: =A104&B104 -> Llay LlaySan Felipe

Sheet Simulador
A1: SIMULADOR DE COMBO DIARIO
A2: ID Combo: | B2: 001
A3: Origen: | B3: Padre Hurtado
A4: Servicio Local: | B4: Quilicura
A5: Bodega (reposicionamiento): | B5: Llay Llay
A6: Destino Sur: | B6: Talca
A7: Punto de Retorno: | B7: Talca
A9: --- DATOS BUSCADOS AUTOMATICAMENTE ---
A10: Tarifa Local: | B10: =INDEX(T1_Locales!C:C,MATCH(B3&B4,T1_Locales!F:F,0))*(1+Supuestos!$B$16) -> 124107
A11: Km Local: | B11: =INDEX(T1_Locales!D:D,MATCH(B3&B4,T1_Locales!F:F,0)) -> 40
A12: Peaje Local: | B12: =INDEX(T1_Locales!E:E,MATCH(B3&B4,T1_Locales!F:F,0)) -> 10000
A13: Km Reposicionamiento: | B13: =IF(B5="Ninguno",0,INDEX(T2_Reposicionamiento!C:C,MATCH(IF(B4="Ninguno",B3,B4)&B5,T2_Reposicionamiento!E:E,0))) -> 80
A14: Peaje Reposicionamiento: | B14: =IF(B5="Ninguno",0,INDEX(T2_Reposicionamiento!D:D,MATCH(IF(B4="Ninguno",B3,B4)&B5,T2_Reposicionamiento!E:E,0))) -> 27100
A15: Tarifa Sur: | B15: =INDEX(T3_DestinosSur!C:C,MATCH(IF(B5="Ninguno",B3,B5)&B6,T3_DestinosSur!F:F,0))*(1+Supuestos!$B$16) -> 602251
A16: Km Sur (ida): | B16: =INDEX(T3_DestinosSur!D:D,MATCH(IF(B5="Ninguno",B3,B5)&B6,T3_DestinosSur!F:F,0)) -> 345
A17: Categoria Peaje Sur: | B17: =INDEX(T3_DestinosSur!E:E,MATCH(IF(B5="Ninguno",B3,B5)&B6,T3_DestinosSur!F:F,0)) -> Larga
A18: Peaje Sur: | B18: =IF(B17="Corta",Supuestos!$B$13,Supuestos!$B$14) -> 52772
A19: Km Retorno (desde PH): | B19: =IF(B7="Ninguno",B16,VLOOKUP(B7,T4_Retornos!A:C,2,0)) -> 250
A20: Tarifa Retorno Base: | B20: =IF(B7="Ninguno",0,VLOOKUP(B7,T4_Retornos!A:C,3,0)*(1+Supuestos!$B$16)) -> 490698
A21: Peaje Retorno: | B21: =IF(B7="Ninguno",B18,IF(B19<Supuestos!$B$15,Supuestos!$B$13,Supuestos!$B$14)) -> 52772
A23: RESULTADO
A24: Km Total: | B24: =B11+B13+B16+B19 -> 715
A25: Días: | B25: =1+IF(((B16+B19)/85+MAX(0,ROUNDUP(((B16+B19)/85)/5,0)-1)*2+4)<=8,0,ROUNDUP(((((B16+B19)/85)+MAX(0,ROUNDUP(((B16+B19)/85)/5,0)-1)*2+4)-8)/12,0)) -> 2
A26: Ingreso Total: | B26: =B10+B15+B20*Supuestos!$B$12 -> 1020776.8
A27: Costos Variables: | B27: =(Supuestos!$B$4/Supuestos!$B$3)*B24+Supuestos!$B$5*B24+Supuestos!$B$6*B25+B12+B14+B18+B21+B26*Supuestos!$B$10 -> 579375.19
A28: Margen Bruto: | B28: =B26-B27 -> 441401.61
A29: Costos Fijos: | B29: =Supuestos!$B$7*B25+Supuestos!$B$8*B25+Supuestos!$B$9*B25 -> 162000
A30: Margen Operativo: | B30: =B28-B29 -> 279401.61
A31: Factoring: | B31: =B26*Supuestos!$B$11 -> 15311.652
A32: Margen antes de Impuestos: | B32: =B30-B31 -> 264089.95
A33: % Margen antes de Impuestos: | B33: =IF(B26=0,0,B32/B26) -> 0.25871469

Sheet Simulador HORIZONTAL
A1: SIMULADOR DE COMBO DIARIO — HORIZONTAL
A3: ID Combo | B3: Origen | C3: Servicio Local | D3: Bodega | E3: Destino Sur | F3: Punto Retorno | G3: Tarifa Local | H3: Km Local | I3: Peaje Local | J3: Km Reposicionamiento | K3: Peaje Reposicionamiento | L3: Tarifa Sur | M3: Km Sur (ida) | N3: Categoria Peaje Sur | O3: Peaje Sur | P3: Km Retorno | Q3: Tarifa Retorno Base | R3: Peaje Retorno | S3: Km Total | T3: Días | U3: Ingreso Total | V3: Costos Variables | W3: Margen Bruto | X3: Costos Fijos | Y3: Margen Operativo | Z3: Factoring | AA3: Margen antes de Impuestos | AB3: % Margen antes de Impuestos
A4: 001 | B4: Padre Hurtado | C4: Quilicura | D4: Llay Llay | E4: Talca | F4: Talca | G4: =INDEX(T1_Locales!C:C,MATCH(B4&C4,T1_Locales!F:F,0))*(1+Supuestos!$B$16) -> 124107 | H4: =INDEX(T1_Locales!D:D,MATCH(B4&C4,T1_Locales!F:F,0)) -> 40 | I4: =INDEX(T1_Locales!E:E,MATCH(B4&C4,T1_Locales!F:F,0)) -> 10000 | J4: =IF(D4="Ninguno",0,INDEX(T2_Reposicionamiento!C:C,MATCH(IF(C4="Ninguno",B4,C4)&D4,T2_Reposicionamiento!E:E,0))) -> 80 | K4: =IF(D4="Ninguno",0,INDEX(T2_Reposicionamiento!D:D,MATCH(IF(C4="Ninguno",B4,C4)&D4,T2_Reposicionamiento!E:E,0))) -> 27100 | L4: =INDEX(T3_DestinosSur!C:C,MATCH(IF(D4="Ninguno",B4,D4)&E4,T3_DestinosSur!F:F,0))*(1+Supuestos!$B$16) -> 602251 | M4: =INDEX(T3_DestinosSur!D:D,MATCH(IF(D4="Ninguno",B4,D4)&E4,T3_DestinosSur!F:F,0)) -> 345 | N4: =INDEX(T3_DestinosSur!E:E,MATCH(IF(D4="Ninguno",B4,D4)&E4,T3_DestinosSur!F:F,0)) -> Larga | O4: =IF(N4="Corta",Supuestos!$B$13,Supuestos!$B$14) -> 52772 | P4: =IF(F4="Ninguno",M4,VLOOKUP(F4,T4_Retornos!A:C,2,0)) -> 250 | Q4: =IF(F4="Ninguno",0,VLOOKUP(F4,T4_Retornos!A:C,3,0)*(1+Supuestos!$B$16)) -> 490698 | R4: =IF(F4="Ninguno",O4,IF(P4<Supuestos!$B$15,Supuestos!$B$13,Supuestos!$B$14)) -> 52772 | S4: =H4+J4+M4+P4 -> 715 | T4: =1+IF(((M4+P4)/85+MAX(0,ROUNDUP(((M4+P4)/85)/5,0)-1)*2+4)<=8,0,ROUNDUP(((((M4+P4)/85)+MAX(0,ROUNDUP(((M4+P4)/85)/5,0)-1)*2+4)-8)/12,0)) -> 2 | U4: =G4+L4+Q4*Supuestos!$B$12 -> 1020776.8 | V4: =(Supuestos!$B$4/Supuestos!$B$3)*S4+Supuestos!$B$5*S4+Supuestos!$B$6*T4+I4+K4+O4+R4+U4*Supuestos!$B$10 -> 579375.19 | W4: =U4-V4 -> 441401.61 | X4: =Supuestos!$B$7*T4+Supuestos!$B$8*T4+Supuestos!$B$9*T4 -> 162000 | Y4: =W4-X4 -> 279401.61 | Z4: =U4*Supuestos!$B$11 -> 15311.652 | AA4: =Y4-Z4 -> 264089.95 | AB4: =IF(U4=0,0,AA4/U4) -> 0.25871469

Sheet T2_Reposicionamiento
A1: Local | B1: Bodega | C1: Km | D1: Peaje | E1: Clave
A2: Quilicura | B2: Llay Llay | C2: 80 | D2: 27100 | E2: =A2&B2 -> QuilicuraLlay Llay
A3: Quilicura | B3: San Bernardo | C3: 32 | D3: 10000 | E3: =A3&B3 -> QuilicuraSan Bernardo
A4: Quilicura | B4: Loginsa | C4: 5 | D4: 0 | E4: =A4&B4 -> QuilicuraLoginsa
A5: Quilicura | B5: Padre Hurtado | C5: 40 | D5: 10000 | E5: =A5&B5 -> QuilicuraPadre Hurtado
A6: Melipilla | B6: Llay Llay | C6: 157 | D6: 35227 | E6: =A6&B6 -> MelipillaLlay Llay
A7: Melipilla | B7: San Bernardo | C7: 60 | D7: 10000 | E7: =A7&B7 -> MelipillaSan Bernardo
A8: Melipilla | B8: Loginsa | C8: 55 | D8: 10000 | E8: =A8&B8 -> MelipillaLoginsa
A9: Melipilla | B9: Padre Hurtado | C9: 50 | D9: 13000 | E9: =A9&B9 -> MelipillaPadre Hurtado
A10: Lampa | B10: Llay Llay | C10: 72 | D10: 21300 | E10: =A10&B10 -> LampaLlay Llay
A11: Lampa | B11: San Bernardo | C11: 45 | D11: 10000 | E11: =A11&B11 -> LampaSan Bernardo
A12: Lampa | B12: Loginsa | C12: 43 | D12: 10000 | E12: =A12&B12 -> LampaLoginsa
A13: Lampa | B13: Padre Hurtado | C13: 46 | D13: 13000 | E13: =A13&B13 -> LampaPadre Hurtado
... A129: Vitacura | B129: Padre Hurtado | C129: 22 | D129: 10000 | E129: =A129&B129 -> VitacuraPadre Hurtado

Sheet T3_DestinosSur
A1: Bodega | B1: Destino | C1: Tarifa | D1: Km (ESTIMADO salvo Talca=real) | E1: Categoria Peaje | F1: Clave
A2: Padre Hurtado | B2: Graneros | C2: 141290 | D2: 80 | E2: =IF(D2<Supuestos!$B$15,"Corta","Larga") -> Corta | F2: =A2&B2 -> Padre HurtadoGraneros
A3: Llay Llay | B3: Graneros | C3: 284347 | D3: 160 | E3: =IF(D3<Supuestos!$B$15,"Corta","Larga") -> Corta | F3: =A3&B3 -> Llay LlayGraneros
A4: San Bernardo | B4: Graneros | C4: 167544 | D4: 60 | E4: =IF(D4<Supuestos!$B$15,"Corta","Larga") -> Corta | F4: =A4&B4 -> San BernardoGraneros
A5: Loginsa | B5: Graneros | C5: 156565 | D5: 72 | E5: =IF(D5<Supuestos!$B$15,"Corta","Larga") -> Corta | F5: =A5&B5 -> LoginsaGraneros
A6: Padre Hurtado | B6: Rancagua | C6: 160384 | D6: 85 | E6: =IF(D6<Supuestos!$B$15,"Corta","Larga") -> Corta | F6: =A6&B6 -> Padre HurtadoRancagua
A7: Llay Llay | B7: Rancagua | C7: 303775 | D7: 171 | E7: =IF(D7<Supuestos!$B$15,"Corta","Larga") -> Larga | F7: =A7&B7 -> Llay LlayRancagua
A8: San Bernardo | B8: Rancagua | C8: 186637 | D8: 70 | E8: =IF(D8<Supuestos!$B$15,"Corta","Larga") -> Corta | F8: =A8&B8 -> San BernardoRancagua
A9: Loginsa | B9: Rancagua | C9: 175658 | D9: 82 | E9: =IF(D9<Supuestos!$B$15,"Corta","Larga") -> Corta | F9: =A9&B9 -> LoginsaRancagua
A10: Padre Hurtado | B10: Requínoa | C10: 219573 | D10: 110 | E10: =IF(D10<Supuestos!$B$15,"Corta","Larga") -> Corta | F10: =A10&B10 -> Padre HurtadoRequínoa
A11: Llay Llay | B11: Requínoa | C11: 362773 | D11: 188 | E11: =IF(D11<Supuestos!$B$15,"Corta","Larga") -> Larga | F11: =A11&B11 -> Llay LlayRequínoa
A12: San Bernardo | B12: Requínoa | C12: 245826 | D12: 87 | E12: =IF(D12<Supuestos!$B$15,"Corta","Larga") -> Corta | F12: =A12&B12 -> San BernardoRequínoa
A13: Loginsa | B13: Requínoa | C13: 234848 | D13: 100 | E13: =IF(D13<Supuestos!$B$15,"Corta","Larga") -> Corta | F13: =A13&B13 -> LoginsaRequínoa
... A97: Loginsa | B97: Cauquenes | C97: 700724 | D97: 352 | E97: =IF(D97<Supuestos!$B$15,"Corta","Larga") -> Larga | F97: =A97&B97 -> LoginsaCauquenes

Sheet T4_Retornos
A1: Retorno | B1: Km desde PH | C1: Tarifa Base (x60%)
A2: Graneros | B2: 80 | C2: 141290
A3: Rancagua | B3: 85 | C3: 160384
A4: Requínoa | B4: 110 | C4: 219573
A5: Pelequén | B5: 123 | C5: 276853
A6: Malloa | B6: 123 | C6: 234848
A7: Rengo | B7: 127 | C7: 219573
A8: San Fernando | B8: 138 | C8: 263488
A9: Peumo | B9: 150 | C9: 278762
A10: Chimbarongo | B10: 155 | C10: 290218
A11: Placilla | B11: 155 | C11: 328405
A12: San Vicente | B12: 155 | C12: 305493
A13: Peralillo | B13: 159 | C13: 305493
... A26: Ninguno | B26: 0 | C26: 0

Sheet T5_Sollem
A1: TARIFARIO SOLLEM — PENDIENTE DE CARGAR
A2: Se usará para el escenario "Sollem ida + TRAST retorno" — el camión ya está en el sur por Sollem, y toma el retorno de TRAST en vez de volver vacío.
A4: Punto (Origen Casablanca) | B4: Destino Sollem | C4: Tarifa Sollem (ida) | D4: Km (ida) | E4: Peaje
