Workbook

Sheet Parametros
A1: PARAMETROS
A3: Parametro | B3: Valor
A4: Total equipos pool (denominador) | B4: 4.5
A5: Remuneracion mensual fija CT (se descuenta de anticipos) | B5: 500000

Sheet Estado de Cuentas
A1: ESTADO DE CUENTAS — Carlos Torres / Pablo (Pool de transporte)
A2: Formulas vivas. n = equipos activos de C.Torres (1 hasta sep-2026, 2 desde oct-2026). Denominador = Parametros!B4. Memoria historica (Oct-25 a Mar-26) en sus hojas originales, sin tocar.
A4: Mes/Año | B4: Utilidad Neta Mes Flota | C4: n (equipos activos CT) | D4: Participación CT (monto) | E4: Anticipos a CT (neto, - $500.000) | F4: Saldo CT (mes) | G4: Saldo CT (acumulado)
A5: Abril-2026 | B5: 11662351 | C5: 1 | D5: =B5/Parametros!$B$4*C5 -> 2591633.6 | E5: PENDIENTE | F5: PENDIENTE | G5: PENDIENTE
A6: Mayo-2026 | B6: 780739 | C6: 1 | D6: =B6/Parametros!$B$4*C6 -> 173497.56 | E6: PENDIENTE | F6: PENDIENTE | G6: PENDIENTE
A7: Junio-2026 | B7: PENDIENTE | C7: 1 | D7: PENDIENTE | E7: =1000000-Parametros!$B$5 -> 500000 | F7: PENDIENTE | G7: PENDIENTE
A8: Julio-2026 | B8: 4612675 | C8: 1 | D8: =B8/Parametros!$B$4*C8 -> 1025038.9 | E8: =900000-Parametros!$B$5 -> 400000 | F8: =D8-E8 -> 625038.89 | G8: =F8 -> 625038.89
A9: Agosto-2026 | B9: 6138282 | C9: 1 | D9: =B9/Parametros!$B$4*C9 -> 1364062.7 | E9: =1080000-Parametros!$B$5 -> 580000 | F9: =D9-E9 -> 784062.67 | G9: =F9+G8 -> 1409101.6
A10: Septiembre-2026 | B10: PENDIENTE | C10: 1 | D10: PENDIENTE | E10: =900000-Parametros!$B$5 -> 400000 | F10: PENDIENTE | G10: PENDIENTE
A11: Octubre-2026 | B11: PENDIENTE | C11: 2 | D11: PENDIENTE | E11: PENDIENTE | F11: PENDIENTE | G11: PENDIENTE
A14: OBSERVACIONES Y PENDIENTES
A15: • Abril: Utilidad Neta oficial confirmada ($11.662.351). Anticipos a CT pendientes -- falta cruce con comprobantes de WhatsApp (anterior al 5-jun).
A16: • Mayo: Utilidad Neta en duda -- existe oficial ($780.739) y borrador previo ($3.072.282), pendiente revisar en detalle cual es correcta. Anticipos pendientes (mismo cruce WhatsApp).
A17: • Junio: Sin Utilidad Neta disponible -- informe de ese mes incompleto (faltan 4 clientes sin capturar). Anticipos SI confirmados ($500.000 neto).
A18: • Julio: Utilidad Neta y Anticipos confirmados completos.
A19: • Agosto: Utilidad Neta confirmada. Anticipos con advertencia -- cartola con hueco real de 4 dias sin cruzar (01-02 y 29-31-ago).
A20: • Septiembre: Sin Utilidad Neta -- informe de resultados aun no construido. Anticipos SI confirmados ($400.000 neto); excluidos correctamente $797.000 (permiso circulacion) + $30.000 (locomocion), 17-sep.
A21: • Octubre: Sin Utilidad Neta (mes en curso). Solo 1 abono real identificado ($820, 3-oct) -- periodo muy parcial, no se aplico el descuento de $500.000 por no ser mes completo.
A22: • Denominador 4,5 equipos confirmado "hasta septiembre" -- no confirmado si cambia desde octubre, se mantuvo igual por defecto, PENDIENTE de confirmar.
A23: • n=2 equipos activos de CT desde octubre, aplicado segun lo indicado -- pendiente que la Utilidad Neta de octubre este disponible.

Sheet Oct a Nov-25
A1: Liquidación (Octubre/Noviembre 2025)
A2: Monto Neto Flete (Ingresos) | C2: 6530000
A3: Factoring | C3: =C2*2% -> 130600
A4: Costo Operacionales | C4: =C5+C6+C7+C8+C9 -> 3528055
A5: - Petróleo Equipo | C5: 2111055
A6: - Base Chofer | C6: 476000
A7: - Viático | C7: 204000
A8: - Peajes | C8: 84000
A9: - Comisión Chofer (10%) | C9: =C2*0.1 -> 653000
A10: Costos Mantención | C10: =C11+C12 -> 3039070
A11: - Repuestos | C11: 2679070
A12: - Mano de obra | C12: 360000
A13: Margen antes Comisión Op. | C13: =C2-C4-C10 -> -37125
A14: Comisión Operaciones | C14: 0
A16: Abonos C. Torres a Sta Berenice | C16: 1000000
A17: Pago Neumaticos C. Torres | C17: 279020
A21: El equipo vendio | C21: =C2 -> 6530000
A22: El equipo gasto | C22: =C4+C10 -> 6567125
A23: C. Torres aporto a los gastos del equipo | C23: =C16+C17 -> 1279020
A24: A favor del equipo | C24: =C21-C22+C23 -> 1241895
A25: Anticipos a C. Torres | C25: =Transferencias!C4+Transferencias!C5 -> 1000000
A28: Saldo a favor de C. Torres | C28: =C24-C25 -> 241895

Sheet Dic-25
A1: Liquidación (Diciembre 2025)
A2: Monto Neto Flete (Ingresos) | C2: 1150000
A3: Factoring | C3: =C2*2% -> 23000
A4: Costo Operacionales | C4: 1034502
A5: - Petróleo Equipos | C5: 562502
A6: - Base Chofer | C6: 231000
A7: - Viático | C7: 84000
A8: - Peajes | C8: 42000
A9: - Comisión Chofer (10%) | C9: 115000
A10: Costos Mantención | C10: 811535
A11: - Repuestos | C11: 811535
A12: - Mano de obra | C12: Falta
A13: Permiso Circulacion Freigthliner | C13: =Transferencias!C11 -> 473000
A15: Margen antes Comisión Op. | C15: =C2-C4-C10-C13 -> -1169037
A16: Comisión Operaciones | C16: 0
A19: El equipo vendio | C19: =C2 -> 1150000
A20: El equipo gasto | C20: =C4+C10+C13 -> 2319037
A21: A favor del equipo | C21: =C19-C20 -> -1169037
A22: Anticipos a C. Torres | C22: =Transferencias!C6+Transferencias!C7+Transferencias!C8+Transferencias!C10 -> 1150000
A23: Saldo a favor de C. Torres | C23: =C21-C22 -> -2319037
A25: Saldo a favor de C. Torres (Acumulado) | C25: ='Oct a Nov-25'!C28+'Dic-25'!C23 -> -2077142

Sheet Ene-26
A1: Liquidación (Enero 2026) GCFF12
A2: Monto Neto Flete (Ingresos) | C2: 5407312
A3: Factoring | C3: =C2*2% -> 108146.24
A4: Costo Operacionales | C4: 3285728
A5: - Petróleo Equipos | C5: 1724997
A6: - Base Chofer | C6: 660000
A7: - Viático | C7: 240000
A8: - Peajes | C8: 120000
A9: - Comisión Chofer (10%) | C9: 540731
A10: Costos Mantención | C10: 1094195
A11: - Repuestos | C11: 1094195
A12: - Mano de obra | C12: Falta
A13: Margen antes Comisión Op. | C13: =C2-C3-C4-C10 -> 919242.76
A14: Comisión Operaciones | C14: =C13*0.2 -> 183848.55
A17: El equipo vendio | C17: =C2 -> 5407312
A18: El equipo gasto | C18: =C4+C10+C14 -> 4563771.6
A19: A favor del equipo | C19: =C17-C18 -> 843540.45
A20: Anticipos a C. Torres | C20: =Transferencias!C14+Transferencias!C16+Transferencias!C18 -> 600000
A21: Saldo a favor de C. Torres | C21: =C19-C20 -> 243540.45
A23: Saldo a favor de C. Torres (Acumulado) | C23: ='Dic-25'!C25+'Ene-26'!C21 -> -1833601.6

Sheet Feb-26
B1: Liquidación (Febrero 2026) Formato de Pool
B2: Ingresos Netos Pool | C2: 25446631
B3: Costo Fijos | C3: 5080000
B4: Costos variables | C4: 16984228
B5: Costo Financiero | C5: =121285+95784+174653 -> 391722
B6: Resultado Neto | C6: =C2-C3-C4-C5 -> 2990681
B8: Saldo a favor de C. Torres - 2 equipos sobre 6 = 33% | C8: =(2/6)*C6 -> 996893.67
B11: Anticipos a C. Torres | C11: =Transferencias!C19+Transferencias!C25 -> 450000
B14: Saldo a favor de C. Torres | C14: =C8-C11 -> 546893.67 | E14: ='Ene-26'!C23 -> -1833601.6
E15: =C14 -> 546893.67
B16: Saldo a favor de C. Torres (Acumulado) | C16: ='Ene-26'!C23+'Feb-26'!C14 -> -1286707.9 | E16: =E14+E15 -> -1286707.9
B19: Cuota 1 Parcela | C19: 1000000

Sheet Mar-26
B1: Liquidación (Febrero 2026) Formato de Pool
B2: Ingresos Netos Pool | C2: 0
B3: Costo Fijos | C3: 0
B4: Costos variables | C4: 0
B5: Resultado Neto | C5: 0
B7: Saldo a favor de C. Torres - 2 equipos sobre 6 = 33% | C7: 0
B10: Anticipos a C. Torres | C10: 0
B13: Saldo a favor de C. Torres | C13: 0
B15: Saldo a favor de C. Torres (Acumulado) | C15: 0
B18: Cuota 2 Parcela | C18: 0
B20: Pagos acumulados Parcela | C20: ='Feb-26'!C19+'Mar-26'!C18 -> 1000000

Sheet Transferencias
A2: FECHA | B2: GLOSA | C2: MONTO | D2: CATEGORIA
A3: 12/11 | B3: 0159957802 Transf de PABLO SEBASTIAN RIQ | C3: 109000 | D3: COMERCIAL RIHE LTDA
A4: 17/11 | B4: 0159957802 Transf de PABLO SEBASTIAN RIQ | C4: 500000 | D4: Anticipo
A5: 24/11 | B5: 0159957802 Transf de PABLO SEBASTIAN RIQ | C5: 500000 | D5: Anticipo
A6: 05/12 | B6: 0774298975 Transf. SOCIEDAD DE TRANSPORTE SA | C6: 200000 | D6: Anticipo
A7: 09/12 | B7: 0774298975 Transf. SOCIEDAD DE TRANSPORTE SA | C7: 300000 | D7: Anticipo
A8: 15/12 | B8: 0159957802 Transf de PABLO SEBASTIAN RIQ | C8: 150000 | D8: Anticipo
A9: 16/12 | B9: 0159957802 Transf de PABLO SEBASTIAN RIQ | C9: 30000 | D9: CAREN ESTACION CENT
A10: 22/12 | B10: 0774298975 Transf. SOCIEDAD DE TRANSPORTE SA | C10: 500000 | D10: Anticipo
A11: 29/12 | B11: 0774298975 Transf. SOCIEDAD DE TRANSPORTE SA | C11: 473000 | D11: Permiso FL
A12: 30/12 | B12: 0159957802 Transf de PABLO SEBASTIAN RIQ | C12: 193000 | D12: MERIGGI TELAS LIMIT y otros
A13: 06/01 | B13: 0159957802 Transf de PABLO SEBASTIAN RIQ | C13: 30000 | D13: Locomocion
A14: 08/01 | B14: 0159957802 Transf de PABLO SEBASTIAN RIQ | C14: 200000 | D14: Anticipo
... A32: 23-03-2026 | B32: 0783031345 TRANSF. GLOBAL SOLUTIONS SPA | C32: 20844 | D32: Repuestos
A35: Total Anticipos | C35: =(C4+C5+C6+C7+C8+C10+C14+C16+C18+C19+C24+C25+C27+C29+C30) -> 5200000
A36: Cuotas Parcela | C36: =+C21 -> 1000000
