Workbook

Sheet Presupuesto
A1: PRESUPUESTO — PARAMETROS FIJOS (editar aqui, se usan en todo el informe)
A2: Cambia un valor aca y se recalcula en Financiero y Operacional automaticamente. No hay numeros sueltos en otras hojas.
A4: Parametro | B4: Valor | C4: Nota
A5: SueldoConductorMes | B5: 660000 | C5: Sueldo fijo mensual bruto por conductor, con contrato desde agosto
A6: ComisionConductorPct | B6: 0.08 | C6: % sobre ventas netas del conductor
A7: ViaticoDia | B7: 12000 | C7: Por dia confirmado con GPS real
A8: CoordinadorOperaciones | B8: 1500000 | C8: Pablo Riquelme, valor fijo
A9: AyudanteOperaciones | B9: 900000 | C9: Sebastian Zuniga, valor fijo
A10: AdministrativoControlGestion | B10: 500000 | C10: Carlos Torres, valor fijo
A11: Arriendo | B11: 450000
A12: Contabilidad | B12: 50000
A13: GastosComunes | B13: 100000
A14: Permisos | B14: 0
A15: ProvisionFiniquitos | B15: 0
A16: UFVigente | B16: 41074 | C16: Editar cada mes
A17: UmbralB_UF | B17: 8000 | C17: Tramo devolucion imp. especifico diesel, confirmar con contador
A18: UmbralC_UF | B18: 20000 | C18: Tramo devolucion imp. especifico diesel
A19: ImpEspecificoPorLitro | B19: 102 | C19: Componente base, $/lt
A20: DiasHabilesMes | B20: 23 | C20: Editar cada mes
A21: FactorIVA | B21: 1.19
I97: =(Presupuesto!$B$8+Presupuesto!$B$9+Presupuesto!$B$10+Presupuesto!$B$11+Presupuesto!$B$12+Presupuesto!$B$13+Presupuesto!$B$14+Presupuesto!$B$15)/5 -> 700000
I98: =(Presupuesto!$B$8+Presupuesto!$B$9+Presupuesto!$B$10+Presupuesto!$B$11+Presupuesto!$B$12+Presupuesto!$B$13+Presupuesto!$B$14+Presupuesto!$B$15)/5 -> 700000
I99: =(Presupuesto!$B$8+Presupuesto!$B$9+Presupuesto!$B$10+Presupuesto!$B$11+Presupuesto!$B$12+Presupuesto!$B$13+Presupuesto!$B$14+Presupuesto!$B$15)/5 -> 700000
I100: =(Presupuesto!$B$8+Presupuesto!$B$9+Presupuesto!$B$10+Presupuesto!$B$11+Presupuesto!$B$12+Presupuesto!$B$13+Presupuesto!$B$14+Presupuesto!$B$15)/5 -> 700000
I101: =(Presupuesto!$B$8+Presupuesto!$B$9+Presupuesto!$B$10+Presupuesto!$B$11+Presupuesto!$B$12+Presupuesto!$B$13+Presupuesto!$B$14+Presupuesto!$B$15)/5 -> 700000
I102: =(Presupuesto!$B$8+Presupuesto!$B$9+Presupuesto!$B$10+Presupuesto!$B$11+Presupuesto!$B$12+Presupuesto!$B$13+Presupuesto!$B$14+Presupuesto!$B$15)/5 -> 700000

Sheet Financiero
A1: INFORME EJECUTIVO — AMBITO FINANCIERO — JULIO 2026
A2: Formulas vivas. Usa los botones +/- (arriba a la izquierda) para expandir cada item y ver su desglose real.
A4: Concepto | B4: Monto
A5: RENTABILIDAD
A6: Ventas netas reales | B6: ='Datos - Servicios Jul'!G45 -> 16728894
A7: Ventas por equipo:
A8: DVDS36 | B8: =SUMIFS('Datos - Servicios Jul'!$G$4:$G$44,'Datos - Servicios Jul'!$J$4:$J$44,"DVDS36") -> 2766807.2
A9: GCFF12 | B9: =SUMIFS('Datos - Servicios Jul'!$G$4:$G$44,'Datos - Servicios Jul'!$J$4:$J$44,"GCFF12") -> 4349600
A10: GKFD84 | B10: =SUMIFS('Datos - Servicios Jul'!$G$4:$G$44,'Datos - Servicios Jul'!$J$4:$J$44,"GKFD84") -> 7313185.7
A11: WR9192 | B11: =SUMIFS('Datos - Servicios Jul'!$G$4:$G$44,'Datos - Servicios Jul'!$J$4:$J$44,"WR9192") -> 747200
A12: XR8555 | B12: =SUMIFS('Datos - Servicios Jul'!$G$4:$G$44,'Datos - Servicios Jul'!$J$4:$J$44,"XR8555") -> 1552100.8
A13: BPLB35 | B13: =SUMIFS('Datos - Servicios Jul'!$G$4:$G$44,'Datos - Servicios Jul'!$J$4:$J$44,"BPLB35") -> 0
A15: Costos de operacion | B15: =B16+B29+B50+B57 -> 11743479
A16: 1. Combustible y costos de ruta | B16: =B18-B27+B28 -> 6087990.5
A17: Combustible bruto (con IVA, Aramco) | B17: =SUMIFS('Datos - Cartola Jul'!$D$5:$D$167,'Datos - Cartola Jul'!$C$5:$C$167,"combustible",'Datos - Cartola Jul'!$B$5:$B$167,"egreso") -> 6159145
A18: Combustible neto IVA (÷1,19) | B18: =B17/Presupuesto!$B$21 -> 5175752.1
A19: Venta anual proyectada (mes x 12) | B19: =B6*12 -> 2.0074673e+08
A20: UF vigente (editar c/mes) | B20: =Presupuesto!$B$16 -> 41074
A21: Venta anual proyectada en UF | B21: =B19/B20 -> 4887.4404
A22: Umbral B UF/año (editar segun SII, hoy <=70%) | B22: =Presupuesto!$B$17 -> 8000
A23: Umbral C UF/año (editar segun SII, hoy <=52,5%) | B23: =Presupuesto!$B$18 -> 20000
A24: % Devolucion imp. especifico (dinamico segun tramo) | B24: =IF(B21<=2400,0.8,IF(B21<=B22,0.7,IF(B21<=B23,0.525,0.31))) -> 0.7
A25: Componente base imp. especifico ($/lt, editar) | B25: =Presupuesto!$B$19 -> 102
A26: Litros julio (camiones+camioneta) | B26: =SUM('Datos - Combustible y GPS'!C4:B18) -> 6349.7
A27: Devolucion impuesto especifico diesel | B27: =B26*B25*B24 -> 453368.58
A28: Peajes (real concesionarias GKFD84+KSRC78 + reembolso resto flota) | B28: =932332+123275+SUMIFS('Datos - Cartola Jul'!$D$5:$D$167,'Datos - Cartola Jul'!$C$5:$C$167,"peajes",'Datos - Cartola Jul'!$B$5:$B$167,"egreso") -> 1365607
A29: 2. Remuneraciones | B29: =B30+B34+B38+B42+B46 -> 4428311.5
A30: 2.1 Felipe Madariaga (conductor) | B30: =B31+B32+B33 -> 1460244.9
A31: Sueldo | B31: =Presupuesto!$B$5 -> 660000
A32: Comision 8% sobre sus ventas netas | B32: =SUMIFS('Datos - Servicios Jul'!$G$4:$G$44,'Datos - Servicios Jul'!$I$4:$I$44,"*Madariaga*")*Presupuesto!$B$6 -> 632244.92
A33: Viatico ($12.000 x dias con servicio) | B33: =Presupuesto!$B$7*SUMIFS('Datos - Servicios Jul'!$L$4:$L$44,'Datos - Servicios Jul'!$I$4:$I$44,"*Madariaga*") -> 168000
A34: 2.2 Francisco Mancilla (conductor) | B34: =B35+B36+B37 -> 1125280
A35: Sueldo | B35: =Presupuesto!$B$5 -> 660000
A36: Comision 8% sobre sus ventas netas | B36: =SUMIFS('Datos - Servicios Jul'!$G$4:$G$44,'Datos - Servicios Jul'!$I$4:$I$44,"*Mancilla*")*Presupuesto!$B$6 -> 381280
A37: Viatico ($12.000 x dias con servicio) | B37: =Presupuesto!$B$7*SUMIFS('Datos - Servicios Jul'!$L$4:$L$44,'Datos - Servicios Jul'!$I$4:$I$44,"*Mancilla*") -> 84000
A38: 2.3 Manuel Madrid (conductor) | B38: =B39+B40+B41 -> 1035072.3
A39: Sueldo | B39: =Presupuesto!$B$5 -> 660000
A40: Comision 8% sobre sus ventas netas | B40: =SUMIFS('Datos - Servicios Jul'!$G$4:$G$44,'Datos - Servicios Jul'!$I$4:$I$44,"*Madrid*")*Presupuesto!$B$6 -> 267072.27
A41: Viatico ($12.000 x dias con servicio) | B41: =Presupuesto!$B$7*SUMIFS('Datos - Servicios Jul'!$L$4:$L$44,'Datos - Servicios Jul'!$I$4:$I$44,"*Madrid*") -> 108000
A42: 2.4 Felipe Vidal (conductor) | B42: =B43+B44+B45 -> 660000
A43: Sueldo | B43: =Presupuesto!$B$5 -> 660000
A44: Comision 8% sobre sus ventas netas | B44: =SUMIFS('Datos - Servicios Jul'!$G$4:$G$44,'Datos - Servicios Jul'!$I$4:$I$44,"*Vidal*")*Presupuesto!$B$6 -> 0
A45: Viatico ($12.000 x dias con servicio) | B45: =Presupuesto!$B$7*SUMIFS('Datos - Servicios Jul'!$L$4:$L$44,'Datos - Servicios Jul'!$I$4:$I$44,"*Vidal*") -> 0
A46: 2.5 Nicolas Vega (conductor reemplazo) | B46: =B47+B48+B49 -> 147714.31
A47: Sueldo proporcional (Presupuesto/20 x dias GPS) | B47: =Presupuesto!$B$5/20*SUMIFS('Datos - Servicios Jul'!$L$4:$L$44,'Datos - Servicios Jul'!$I$4:$I$44,"*Vega*") -> 66000
A48: Comision 8% sobre sus ventas netas | B48: =SUMIFS('Datos - Servicios Jul'!$G$4:$G$44,'Datos - Servicios Jul'!$I$4:$I$44,"*Vega*")*Presupuesto!$B$6 -> 57714.307
A49: Viatico ($12.000 x dias con servicio) | B49: =Presupuesto!$B$7*SUMIFS('Datos - Servicios Jul'!$L$4:$L$44,'Datos - Servicios Jul'!$I$4:$I$44,"*Vega*") -> 24000
A50: 3. Mantencion | B50: =B51+B52+B53+B54+B55 -> 0
A51: 3.1 DVDS36 | B51: =SUMIFS('Datos - Cartola Jul'!$D$5:$D$167,'Datos - Cartola Jul'!$C$5:$C$167,"mantencion",'Datos - Cartola Jul'!$B$5:$B$167,"egreso",'Datos - Cartola Jul'!$F$5:$F$167,'Datos - Combustible y GPS'!A4)/Presupuesto!$B$21 -> 0
A52: 3.2 GCFF12 | B52: =SUMIFS('Datos - Cartola Jul'!$D$5:$D$167,'Datos - Cartola Jul'!$C$5:$C$167,"mantencion",'Datos - Cartola Jul'!$B$5:$B$167,"egreso",'Datos - Cartola Jul'!$F$5:$F$167,'Datos - Combustible y GPS'!A5)/Presupuesto!$B$21 -> 0
A53: 3.3 GKFD84 | B53: =SUMIFS('Datos - Cartola Jul'!$D$5:$D$167,'Datos - Cartola Jul'!$C$5:$C$167,"mantencion",'Datos - Cartola Jul'!$B$5:$B$167,"egreso",'Datos - Cartola Jul'!$F$5:$F$167,'Datos - Combustible y GPS'!A6)/Presupuesto!$B$21 -> 0
A54: 3.4 WR9192 | B54: =SUMIFS('Datos - Cartola Jul'!$D$5:$D$167,'Datos - Cartola Jul'!$C$5:$C$167,"mantencion",'Datos - Cartola Jul'!$B$5:$B$167,"egreso",'Datos - Cartola Jul'!$F$5:$F$167,'Datos - Combustible y GPS'!A8)/Presupuesto!$B$21 -> 0
A55: 3.5 XR8555 | B55: =SUMIFS('Datos - Cartola Jul'!$D$5:$D$167,'Datos - Cartola Jul'!$C$5:$C$167,"mantencion",'Datos - Cartola Jul'!$B$5:$B$167,"egreso",'Datos - Cartola Jul'!$F$5:$F$167,'Datos - Combustible y GPS'!A9)/Presupuesto!$B$21 -> 0
A56: Ref. camionetas (no suman al total "solo camiones"): KSRC78 | B56: =SUMIFS('Datos - Cartola Jul'!$D$5:$D$167,'Datos - Cartola Jul'!$C$5:$C$167,"mantencion",'Datos - Cartola Jul'!$B$5:$B$167,"egreso",'Datos - Cartola Jul'!$F$5:$F$167,'Datos - Combustible y GPS'!A7)/Presupuesto!$B$21 -> 0
A57: 4. Otros costos operacionales | B57: =B58+B59+B60 -> 1227177
A58: Gastos de representacion | B58: =SUMIFS('Datos - Cartola Jul'!$D$5:$D$167,'Datos - Cartola Jul'!$C$5:$C$167,"gastos_representacion",'Datos - Cartola Jul'!$B$5:$B$167,"egreso") -> 31955
A59: Otro / sin clasificar (ver concepto real en Datos-Cartola col. G) | B59: =SUMIFS('Datos - Cartola Jul'!$D$5:$D$167,'Datos - Cartola Jul'!$C$5:$C$167,"otro",'Datos - Cartola Jul'!$B$5:$B$167,"egreso")+SUMIFS('Datos - Cartola Jul'!$D$5:$D$167,'Datos - Cartola Jul'!$C$5:$C$167,"otro_por_clasificar",'Datos - Cartola Jul'!$B$5:$B$167,"egreso") -> 1185751
A60: IVA menor pagado | B60: =SUMIFS('Datos - Cartola Jul'!$D$5:$D$167,'Datos - Cartola Jul'!$C$5:$C$167,"iva",'Datos - Cartola Jul'!$B$5:$B$167,"egreso") -> 9471
A62: MARGEN OPERACIONAL ($) | B62: =B6-B15 -> 4985414.7
A63: MARGEN OPERACIONAL (%) | B63: =B62/B6 -> 0.29801222
A65: Margen Bruto ($) [Ventas - Combustible - Comision - Viatico - Peajes] | B65: =B6-B18-(B32+B36+B40+B44+B48)-(B33+B37+B41+B45+B49)-B28-B73-B67 -> 7542538.2
A66: Margen Bruto (%) | B66: =B65/B6 -> 0.45086891
A67: Gasto Financiero Factoring (3% Sollem + 3% Serlogin, sobre facturado real RCV) | B67: 372740
A68: MARGEN NETO ($) | B68: =B62-B67 -> 4612674.7
A69: MARGEN NETO (%) | B69: =B68/B6 -> 0.27573101
A70: EBITDA ($) [= Margen Operacional, no hay depreciacion calculada aun] | B70: =B62 -> 4985414.7
A71: EBITDA (%) | B71: =B70/B6 -> 0.29801222
A73: Mantencion programada ($40/km x 13.748,6 km reales, mantencion real=$0) | B73: 549945
A75: 5. Costo Fijo Estructural (acumulable, fuera del margen del mes)
A76: Coordinador Operaciones | B76: =Presupuesto!$B$8 -> 1500000
A77: Ayudante Operaciones | B77: =Presupuesto!$B$9 -> 900000
A78: Administrativo / Control de Gestion | B78: =Presupuesto!$B$10 -> 500000
A79: Arriendo | B79: =Presupuesto!$B$11 -> 450000
A80: Contabilidad | B80: =Presupuesto!$B$12 -> 50000
A81: Permisos | B81: =Presupuesto!$B$14 -> 0
A82: Gastos comunes | B82: =Presupuesto!$B$13 -> 100000
A83: Provision finiquitos | B83: =Presupuesto!$B$15 -> 0
A84: Sueldo base conductor (Madariaga) | B84: =Presupuesto!$B$5 -> 660000
A85: Sueldo base conductor (Mancilla) | B85: =Presupuesto!$B$5 -> 660000
A86: Sueldo base conductor (Madrid) | B86: =Presupuesto!$B$5 -> 660000
A87: Sueldo base conductor (Vidal) | B87: =Presupuesto!$B$5 -> 660000
A88: TOTAL Costo Fijo (para punto de equilibrio) | B88: =B76+B77+B78+B79+B80+B81+B82+B83+B84+B85+B86+B87 -> 6140000
A90: LIQUIDEZ
A91: Ingresos reales a caja | B91: =SUMIFS('Datos - Cartola Jul'!$D$5:$D$167,'Datos - Cartola Jul'!$B$5:$B$167,"ingreso") -> 20169108
A92: Egresos reales (incl. capex/retiros) | B92: =SUMIFS('Datos - Cartola Jul'!$D$5:$D$167,'Datos - Cartola Jul'!$B$5:$B$167,"egreso") -> 15633743
A93: FLUJO NETO DEL MES | B93: =B91-B92 -> 4535365
A95: CxC — Mora Sollem a recuperar (no es costo) | B95: 0
A97: SOLVENCIA: Global no tiene deudas vigentes a julio 2026 (confirmado por Carlos).
A99: UNIDAD DE NEGOCIO POR EQUIPO
A100: Sueldo/Viatico por equipo = dias que ESE equipo opero segun GPS. Comision por equipo = 8% de la venta de ESE equipo. Costo Fijo Estructural se reparte en partes iguales entre los 6 camiones (existe se use o no el equipo).
A101: Patente | B101: Ventas | C101: Combustible | D101: Km GPS | E101: Mantencion | F101: Sueldo conductor | G101: Comision | H101: Viatico | I101: Costo Fijo (1/6) | J101: Utilidad Operacional | K101: $/km | L101: Utilidad/dia | M101: Margen Bruto % | N101: Margen Operacional % | O101: Gasto Financiero (prop. Sollem) | P101: Margen Neto | Q101: Margen Neto %
A102: DVDS36 | B102: =SUMIFS('Datos - Servicios Jul'!$G$4:$G$44,'Datos - Servicios Jul'!$J$4:$J$44,"DVDS36") -> 2766807.2 | C102: ='Datos - Combustible y GPS'!D4 -> 1202490 | D102: =IF(ISNUMBER('Datos - Combustible y GPS'!E4),'Datos - Combustible y GPS'!E4,0) -> 3682.959 | E102: =SUMIFS('Datos - Cartola Jul'!$D$5:$D$167,'Datos - Cartola Jul'!$C$5:$C$167,"mantencion",'Datos - Cartola Jul'!$B$5:$B$167,"egreso",'Datos - Cartola Jul'!$F$5:$F$167,A102)/Presupuesto!$B$21 -> 0 | F102: =Presupuesto!$B$5/20*COUNTIF('Datos - GPS Dias'!$A$5:$A$70,A102) -> 561000 | G102: =B102*Presupuesto!$B$6 -> 221344.58 | H102: =Presupuesto!$B$7*COUNTIF('Datos - GPS Dias'!$A$5:$A$70,A102) -> 204000 | I102: =(Presupuesto!$B$8+Presupuesto!$B$9+Presupuesto!$B$10+Presupuesto!$B$11+Presupuesto!$B$12+Presupuesto!$B$13+Presupuesto!$B$14+Presupuesto!$B$15)/6 -> 583333.33 | J102: =B102-C102-E102-F102-G102-H102-I102 -> -5360.7078 | K102: =IFERROR(B102/D102,"") -> 751.24572 | L102: =IFERROR(J102/COUNTIF('Datos - GPS Dias'!$A$5:$A$70,A102),"") -> -315.33575 | M102: =IFERROR((B102-C102-G102-H102)/B102,"") -> 0.41165594 | N102: =IFERROR(J102/B102,"") -> -0.0019375068 | O102: =IFERROR(SUMIFS('Datos - Servicios Jul'!$G$4:$G$44,'Datos - Servicios Jul'!$J$4:$J$44,A102,'Datos - Servicios Jul'!$C$4:$C$44,"Sollem")/SUMIFS('Datos - Servicios Jul'!$G$4:$G$44,'Datos - Servicios Jul'!$C$4:$C$44,"Sollem")*$B$67,0) -> 0 | P102: =J102-O102 -> -5360.7078 | Q102: =IFERROR(P102/B102,"") -> -0.0019375068
A103: GCFF12 | B103: =SUMIFS('Datos - Servicios Jul'!$G$4:$G$44,'Datos - Servicios Jul'!$J$4:$J$44,"GCFF12") -> 4349600 | C103: ='Datos - Combustible y GPS'!D5 -> 1467626 | D103: =IF(ISNUMBER('Datos - Combustible y GPS'!E5),'Datos - Combustible y GPS'!E5,0) -> 2450.405 | E103: =SUMIFS('Datos - Cartola Jul'!$D$5:$D$167,'Datos - Cartola Jul'!$C$5:$C$167,"mantencion",'Datos - Cartola Jul'!$B$5:$B$167,"egreso",'Datos - Cartola Jul'!$F$5:$F$167,A103)/Presupuesto!$B$21 -> 0 | F103: =Presupuesto!$B$5/20*COUNTIF('Datos - GPS Dias'!$A$5:$A$70,A103) -> 330000 | G103: =B103*Presupuesto!$B$6 -> 347968 | H103: =Presupuesto!$B$7*COUNTIF('Datos - GPS Dias'!$A$5:$A$70,A103) -> 120000 | I103: =(Presupuesto!$B$8+Presupuesto!$B$9+Presupuesto!$B$10+Presupuesto!$B$11+Presupuesto!$B$12+Presupuesto!$B$13+Presupuesto!$B$14+Presupuesto!$B$15)/6 -> 583333.33 | J103: =B103-C103-E103-F103-G103-H103-I103 -> 1500672.7 | K103: =IFERROR(B103/D103,"") -> 1775.0535 | L103: =IFERROR(J103/COUNTIF('Datos - GPS Dias'!$A$5:$A$70,A103),"") -> 150067.27 | M103: =IFERROR((B103-C103-G103-H103)/B103,"") -> 0.55499494 | N103: =IFERROR(J103/B103,"") -> 0.34501395 | O103: =IFERROR(SUMIFS('Datos - Servicios Jul'!$G$4:$G$44,'Datos - Servicios Jul'!$J$4:$J$44,A103,'Datos - Servicios Jul'!$C$4:$C$44,"Sollem")/SUMIFS('Datos - Servicios Jul'!$G$4:$G$44,'Datos - Servicios Jul'!$C$4:$C$44,"Sollem")*$B$67,0) -> 77785.496 | P103: =J103-O103 -> 1422887.2 | Q103: =IFERROR(P103/B103,"") -> 0.32713058
A104: GKFD84 | B104: =SUMIFS('Datos - Servicios Jul'!$G$4:$G$44,'Datos - Servicios Jul'!$J$4:$J$44,"GKFD84") -> 7313185.7 | C104: ='Datos - Combustible y GPS'!D6 -> 3114070 | D104: =IF(ISNUMBER('Datos - Combustible y GPS'!E6),'Datos - Combustible y GPS'!E6,0) -> 5277.71 | E104: =SUMIFS('Datos - Cartola Jul'!$D$5:$D$167,'Datos - Cartola Jul'!$C$5:$C$167,"mantencion",'Datos - Cartola Jul'!$B$5:$B$167,"egreso",'Datos - Cartola Jul'!$F$5:$F$167,A104)/Presupuesto!$B$21 -> 0 | F104: =Presupuesto!$B$5/20*COUNTIF('Datos - GPS Dias'!$A$5:$A$70,A104) -> 594000 | G104: =B104*Presupuesto!$B$6 -> 585054.86 | H104: =Presupuesto!$B$7*COUNTIF('Datos - GPS Dias'!$A$5:$A$70,A104) -> 216000 | I104: =(Presupuesto!$B$8+Presupuesto!$B$9+Presupuesto!$B$10+Presupuesto!$B$11+Presupuesto!$B$12+Presupuesto!$B$13+Presupuesto!$B$14+Presupuesto!$B$15)/6 -> 583333.33 | J104: =B104-C104-E104-F104-G104-H104-I104 -> 2220727.5 | K104: =IFERROR(B104/D104,"") -> 1385.674 | L104: =IFERROR(J104/COUNTIF('Datos - GPS Dias'!$A$5:$A$70,A104),"") -> 123373.75 | M104: =IFERROR((B104-C104-G104-H104)/B104,"") -> 0.46464851 | N104: =IFERROR(J104/B104,"") -> 0.30366076 | O104: =IFERROR(SUMIFS('Datos - Servicios Jul'!$G$4:$G$44,'Datos - Servicios Jul'!$J$4:$J$44,A104,'Datos - Servicios Jul'!$C$4:$C$44,"Sollem")/SUMIFS('Datos - Servicios Jul'!$G$4:$G$44,'Datos - Servicios Jul'!$C$4:$C$44,"Sollem")*$B$67,0) -> 261643.34 | P104: =J104-O104 -> 1959084.2 | Q104: =IFERROR(P104/B104,"") -> 0.26788383
A105: WR9192 | B105: =SUMIFS('Datos - Servicios Jul'!$G$4:$G$44,'Datos - Servicios Jul'!$J$4:$J$44,"WR9192") -> 747200 | C105: ='Datos - Combustible y GPS'!D8 -> 431517 | D105: =IF(ISNUMBER('Datos - Combustible y GPS'!E8),'Datos - Combustible y GPS'!E8,0) -> 933.913 | E105: =SUMIFS('Datos - Cartola Jul'!$D$5:$D$167,'Datos - Cartola Jul'!$C$5:$C$167,"mantencion",'Datos - Cartola Jul'!$B$5:$B$167,"egreso",'Datos - Cartola Jul'!$F$5:$F$167,A105)/Presupuesto!$B$21 -> 0 | F105: =Presupuesto!$B$5/20*COUNTIF('Datos - GPS Dias'!$A$5:$A$70,A105) -> 363000 | G105: =B105*Presupuesto!$B$6 -> 59776 | H105: =Presupuesto!$B$7*COUNTIF('Datos - GPS Dias'!$A$5:$A$70,A105) -> 132000 | I105: =(Presupuesto!$B$8+Presupuesto!$B$9+Presupuesto!$B$10+Presupuesto!$B$11+Presupuesto!$B$12+Presupuesto!$B$13+Presupuesto!$B$14+Presupuesto!$B$15)/6 -> 583333.33 | J105: =B105-C105-E105-F105-G105-H105-I105 -> -822426.33 | K105: =IFERROR(B105/D105,"") -> 800.07453 | L105: =IFERROR(J105/COUNTIF('Datos - GPS Dias'!$A$5:$A$70,A105),"") -> -74766.03 | M105: =IFERROR((B105-C105-G105-H105)/B105,"") -> 0.16582843 | N105: =IFERROR(J105/B105,"") -> -1.1006776 | O105: =IFERROR(SUMIFS('Datos - Servicios Jul'!$G$4:$G$44,'Datos - Servicios Jul'!$J$4:$J$44,A105,'Datos - Servicios Jul'!$C$4:$C$44,"Sollem")/SUMIFS('Datos - Servicios Jul'!$G$4:$G$44,'Datos - Servicios Jul'!$C$4:$C$44,"Sollem")*$B$67,0) -> 33311.166 | P105: =J105-O105 -> -855737.5 | Q105: =IFERROR(P105/B105,"") -> -1.145259
A106: XR8555 | B106: =SUMIFS('Datos - Servicios Jul'!$G$4:$G$44,'Datos - Servicios Jul'!$J$4:$J$44,"XR8555") -> 1552100.8 | C106: ='Datos - Combustible y GPS'!D9 -> 734515 | D106: =IF(ISNUMBER('Datos - Combustible y GPS'!E9),'Datos - Combustible y GPS'!E9,0) -> 1403.627 | E106: =SUMIFS('Datos - Cartola Jul'!$D$5:$D$167,'Datos - Cartola Jul'!$C$5:$C$167,"mantencion",'Datos - Cartola Jul'!$B$5:$B$167,"egreso",'Datos - Cartola Jul'!$F$5:$F$167,A106)/Presupuesto!$B$21 -> 0 | F106: =Presupuesto!$B$5/20*COUNTIF('Datos - GPS Dias'!$A$5:$A$70,A106) -> 297000 | G106: =B106*Presupuesto!$B$6 -> 124168.07 | H106: =Presupuesto!$B$7*COUNTIF('Datos - GPS Dias'!$A$5:$A$70,A106) -> 108000 | I106: =(Presupuesto!$B$8+Presupuesto!$B$9+Presupuesto!$B$10+Presupuesto!$B$11+Presupuesto!$B$12+Presupuesto!$B$13+Presupuesto!$B$14+Presupuesto!$B$15)/6 -> 583333.33 | J106: =B106-C106-E106-F106-G106-H106-I106 -> -294915.56 | K106: =IFERROR(B106/D106,"") -> 1105.7787 | L106: =IFERROR(J106/COUNTIF('Datos - GPS Dias'!$A$5:$A$70,A106),"") -> -32768.396 | M106: =IFERROR((B106-C106-G106-H106)/B106,"") -> 0.37717767 | N106: =IFERROR(J106/B106,"") -> -0.19001057 | O106: =IFERROR(SUMIFS('Datos - Servicios Jul'!$G$4:$G$44,'Datos - Servicios Jul'!$J$4:$J$44,A106,'Datos - Servicios Jul'!$C$4:$C$44,"Sollem")/SUMIFS('Datos - Servicios Jul'!$G$4:$G$44,'Datos - Servicios Jul'!$C$4:$C$44,"Sollem")*$B$67,0) -> 0 | P106: =J106-O106 -> -294915.56 | Q106: =IFERROR(P106/B106,"") -> -0.19001057
A107: BPLB35 | B107: =SUMIFS('Datos - Servicios Jul'!$G$4:$G$44,'Datos - Servicios Jul'!$J$4:$J$44,"BPLB35") -> 0 | C107: 0 | D107: 0.145 | E107: =SUMIFS('Datos - Cartola Jul'!$D$5:$D$167,'Datos - Cartola Jul'!$C$5:$C$167,"mantencion",'Datos - Cartola Jul'!$B$5:$B$167,"egreso",'Datos - Cartola Jul'!$F$5:$F$167,A107)/Presupuesto!$B$21 -> 0 | F107: =Presupuesto!$B$5/20*COUNTIF('Datos - GPS Dias'!$A$5:$A$70,A107) -> 33000 | G107: =B107*Presupuesto!$B$6 -> 0 | H107: =Presupuesto!$B$7*COUNTIF('Datos - GPS Dias'!$A$5:$A$70,A107) -> 12000 | I107: =(Presupuesto!$B$8+Presupuesto!$B$9+Presupuesto!$B$10+Presupuesto!$B$11+Presupuesto!$B$12+Presupuesto!$B$13+Presupuesto!$B$14+Presupuesto!$B$15)/6 -> 583333.33 | J107: =B107-C107-E107-F107-G107-H107-I107 -> -628333.33 | K107: =IFERROR(B107/D107,"") -> 0 | L107: =IFERROR(J107/COUNTIF('Datos - GPS Dias'!$A$5:$A$70,A107),"") -> -628333.33 | M107: =IFERROR((B107-C107-G107-H107)/B107,"") | N107: =IFERROR(J107/B107,"") | O107: =IFERROR(SUMIFS('Datos - Servicios Jul'!$G$4:$G$44,'Datos - Servicios Jul'!$J$4:$J$44,A107,'Datos - Servicios Jul'!$C$4:$C$44,"Sollem")/SUMIFS('Datos - Servicios Jul'!$G$4:$G$44,'Datos - Servicios Jul'!$C$4:$C$44,"Sollem")*$B$73,0) -> 0 | P107: =J107-O107 -> -628333.33 | Q107: =IFERROR(P107/B107,"")
A108: TOTAL | B108: =B102+B103+B104+B105+B106+B107 -> 16728894 | C108: =C102+C103+C104+C105+C106+C107 -> 6950218 | E108: =E102+E103+E104+E105+E106+E107 -> 0 | F108: =F102+F103+F104+F105+F106+F107 -> 2178000 | G108: =G102+G103+G104+G105+G106+G107 -> 1338311.5 | H108: =H102+H103+H104+H105+H106+H107 -> 792000 | I108: =I102+I103+I104+I105+I106+I107 -> 3500000 | J108: =J102+J103+J104+J105+J106+J107 -> 1970364.3 | O108: =O102+O103+O104+O105+O106+O107 -> 372740 | P108: =P102+P103+P104+P105+P106+P107 -> 1597624.3
A110: PUNTO DE EQUILIBRIO
A111: Listado de costos considerados:
...

Sheet Comercial
A1: INFORME EJECUTIVO — AMBITO COMERCIAL — JULIO 2026
A2: Fuente: hoja de servicios de Pablo (julio) + historico real de servicios_piloto (Supabase) para Fidelizacion.
A4: PILAR 1 — DISTRIBUCION / CONCENTRACION DE CARTERA (reemplaza participacion de mercado)
A5: Cliente | B5: Ventas julio | C5: % de la cartera
A6: Sollem | B6: 9949471 | C6: =B6/$B$13 -> 0.49978799
A7: Nano Presmita | B7: 3869500 | C7: =B7/$B$13 -> 0.19437512
A8: Serlogin | B8: 3099712 | C8: =B8/$B$13 -> 0.15570665
A9: Trans Luciano | B9: 1249500 | C9: =B9/$B$13 -> 0.062765658
A10: Andrea Alacon | B10: 1240200 | C10: =B10/$B$13 -> 0.062298495
A11: Rata | B11: 380000 | C11: =B11/$B$13 -> 0.019088395
A12: Victor Frutillero | B12: 119000 | C12: =B12/$B$13 -> 0.0059776817
A13: TOTAL | B13: =SUM(B6:B12) -> 19907383
A17: PILAR 2 — FIDELIZACION (sin contratos firmados)
A18: Cliente | B18: Antiguedad (desde) | C18: Meses con actividad | D18: Consistencia | E18: Valor de vida acumulado
A23: Clientes con 1 solo mes de actividad (recien incorporados, aun sin antiguedad real): Danilo Nunez, Serlogin, Agricola Don Hugo, TRAST Logistics, Kapital Box, Rucaray.
A25: PILAR 3 — DIVERSIFICACION
A26: Clientes activos en julio
A27: Clientes nuevos incorporados en julio (vs. meses previos)
A28: % dependencia del cliente principal (Sollem)

Sheet Operacional
A1: INFORME EJECUTIVO — AMBITO OPERACIONAL — JULIO 2026
A2: Formulas vivas. Mantencion por equipo requiere que completes la columna Patente en Datos-Cartola Jul.
A4: COMBUSTIBLE — camiones + camionetas (Aramco+Copec)
A5: Patente | B5: Tipo | C5: Litros | D5: Monto $ | E5: % del total
A6: ='Datos - Combustible y GPS'!A4 -> DVDS36 | B6: ='Datos - Combustible y GPS'!B4 -> Camión | C6: ='Datos - Combustible y GPS'!C4 -> 1011 | D6: ='Datos - Combustible y GPS'!D4 -> 1202490 | E6: =D6/SUM('Datos - Combustible y GPS'!D4:D10) -> 0.15893916
A7: ='Datos - Combustible y GPS'!A5 -> GCFF12 | B7: ='Datos - Combustible y GPS'!B5 -> Camión | C7: ='Datos - Combustible y GPS'!C5 -> 1235.6 | D7: ='Datos - Combustible y GPS'!D5 -> 1467626 | E7: =D7/SUM('Datos - Combustible y GPS'!D4:D10) -> 0.19398352
A8: ='Datos - Combustible y GPS'!A6 -> GKFD84 | B8: ='Datos - Combustible y GPS'!B6 -> Camión | C8: ='Datos - Combustible y GPS'!C6 -> 2605.4 | D8: ='Datos - Combustible y GPS'!D6 -> 3114070 | E8: =D8/SUM('Datos - Combustible y GPS'!D4:D10) -> 0.41160232
A9: ='Datos - Combustible y GPS'!A7 -> KSRC78 | B9: ='Datos - Combustible y GPS'!B7 -> Camioneta | C9: ='Datos - Combustible y GPS'!C7 -> 456.8 | D9: ='Datos - Combustible y GPS'!D7 -> 565507 | E9: =D9/SUM('Datos - Combustible y GPS'!D4:D10) -> 0.07474591
A10: ='Datos - Combustible y GPS'!A8 -> WR9192 | B10: ='Datos - Combustible y GPS'!B8 -> Camión | C10: ='Datos - Combustible y GPS'!C8 -> 369.9 | D10: ='Datos - Combustible y GPS'!D8 -> 431517 | E10: =D10/SUM('Datos - Combustible y GPS'!D4:D10) -> 0.057035776
A11: ='Datos - Combustible y GPS'!A9 -> XR8555 | B11: ='Datos - Combustible y GPS'!B9 -> Camión | C11: ='Datos - Combustible y GPS'!C9 -> 629.9 | D11: ='Datos - Combustible y GPS'!D9 -> 734515 | E11: =D11/SUM('Datos - Combustible y GPS'!D4:D10) -> 0.097084549
A12: ='Datos - Combustible y GPS'!A10 -> JYJV21 | B12: ='Datos - Combustible y GPS'!B10 -> Camioneta | C12: ='Datos - Combustible y GPS'!C10 -> 41.1 | D12: ='Datos - Combustible y GPS'!D10 -> 50000 | E12: =D12/SUM('Datos - Combustible y GPS'!D4:D10) -> 0.006608752
A14: RENDIMIENTO km/lt — SOLO CAMIONES (excluye camionetas KSRC78, JYJV21)
A15: Patente | B15: Litros | C15: Km GPS | D15: Rendimiento (km/lt)
A16: =IF('Datos - Combustible y GPS'!B4="Camión",'Datos - Combustible y GPS'!A4,"") -> DVDS36 | B16: =IF('Datos - Combustible y GPS'!B4="Camión",'Datos - Combustible y GPS'!C4,"") -> 1011 | C16: =IF(AND('Datos - Combustible y GPS'!B4="Camión",ISNUMBER('Datos - Combustible y GPS'!E4)),'Datos - Combustible y GPS'!E4,"") -> 3682.959 | D16: =IFERROR(C16/B16,"") -> 3.6428872
A17: =IF('Datos - Combustible y GPS'!B5="Camión",'Datos - Combustible y GPS'!A5,"") -> GCFF12 | B17: =IF('Datos - Combustible y GPS'!B5="Camión",'Datos - Combustible y GPS'!C5,"") -> 1235.6 | C17: =IF(AND('Datos - Combustible y GPS'!B5="Camión",ISNUMBER('Datos - Combustible y GPS'!E5)),'Datos - Combustible y GPS'!E5,"") -> 2450.405 | D17: =IFERROR(C17/B17,"") -> 1.9831701
A18: =IF('Datos - Combustible y GPS'!B6="Camión",'Datos - Combustible y GPS'!A6,"") -> GKFD84 | B18: =IF('Datos - Combustible y GPS'!B6="Camión",'Datos - Combustible y GPS'!C6,"") -> 2605.4 | C18: =IF(AND('Datos - Combustible y GPS'!B6="Camión",ISNUMBER('Datos - Combustible y GPS'!E6)),'Datos - Combustible y GPS'!E6,"") -> 5277.71 | D18: =IFERROR(C18/B18,"") -> 2.0256813
A19: =IF('Datos - Combustible y GPS'!B8="Camión",'Datos - Combustible y GPS'!A8,"") -> WR9192 | B19: =IF('Datos - Combustible y GPS'!B8="Camión",'Datos - Combustible y GPS'!C8,"") -> 369.9 | C19: =IF(AND('Datos - Combustible y GPS'!B8="Camión",ISNUMBER('Datos - Combustible y GPS'!E8)),'Datos - Combustible y GPS'!E8,"") -> 933.913 | D19: =IFERROR(C19/B19,"") -> 2.5247716
A20: =IF('Datos - Combustible y GPS'!B9="Camión",'Datos - Combustible y GPS'!A9,"") -> XR8555 | B20: =IF('Datos - Combustible y GPS'!B9="Camión",'Datos - Combustible y GPS'!C9,"") -> 629.9 | C20: =IF(AND('Datos - Combustible y GPS'!B9="Camión",ISNUMBER('Datos - Combustible y GPS'!E9)),'Datos - Combustible y GPS'!E9,"") -> 1403.627 | D20: =IFERROR(C20/B20,"") -> 2.2283331
A22: =IF('Datos - Combustible y GPS'!B10="Camión",'Datos - Combustible y GPS'!A10,"") | B22: =IF('Datos - Combustible y GPS'!B10="Camión",'Datos - Combustible y GPS'!C10,"") | C22: =IF(AND('Datos - Combustible y GPS'!B10="Camión",ISNUMBER('Datos - Combustible y GPS'!E10)),'Datos - Combustible y GPS'!E10,"") | D22: =IFERROR(C22/B22,"")
A24: MANTENCION — SOLO CAMIONES, desglose por equipo (neto IVA)
A25: Completa la columna Patente en Datos-Cartola Jul para que esto se llene solo.
A26: Patente (camión) | B26: Mantencion neta IVA
A27: DVDS36 | B27: =SUMIFS('Datos - Cartola Jul'!$D$5:$D$167,'Datos - Cartola Jul'!$C$5:$C$167,"mantencion",'Datos - Cartola Jul'!$B$5:$B$167,"egreso",'Datos - Cartola Jul'!$F$5:$F$167,A27)/Presupuesto!$B$21 -> 0
A28: GCFF12 | B28: =SUMIFS('Datos - Cartola Jul'!$D$5:$D$167,'Datos - Cartola Jul'!$C$5:$C$167,"mantencion",'Datos - Cartola Jul'!$B$5:$B$167,"egreso",'Datos - Cartola Jul'!$F$5:$F$167,A28)/Presupuesto!$B$21 -> 0
A29: GKFD84 | B29: =SUMIFS('Datos - Cartola Jul'!$D$5:$D$167,'Datos - Cartola Jul'!$C$5:$C$167,"mantencion",'Datos - Cartola Jul'!$B$5:$B$167,"egreso",'Datos - Cartola Jul'!$F$5:$F$167,A29)/Presupuesto!$B$21 -> 0
A30: WR9192 | B30: =SUMIFS('Datos - Cartola Jul'!$D$5:$D$167,'Datos - Cartola Jul'!$C$5:$C$167,"mantencion",'Datos - Cartola Jul'!$B$5:$B$167,"egreso",'Datos - Cartola Jul'!$F$5:$F$167,A30)/Presupuesto!$B$21 -> 0
A31: XR8555 | B31: =SUMIFS('Datos - Cartola Jul'!$D$5:$D$167,'Datos - Cartola Jul'!$C$5:$C$167,"mantencion",'Datos - Cartola Jul'!$B$5:$B$167,"egreso",'Datos - Cartola Jul'!$F$5:$F$167,A31)/Presupuesto!$B$21 -> 0
A32: TOTAL mantencion camiones | B32: =B27+B28+B29+B30+B31 -> 0
A33: Mantencion $/km (flota camiones) -- solo referencia, NO se usa en el informe de resultados | B33: =B32/SUMIFS('Datos - Combustible y GPS'!E4:E10,'Datos - Combustible y GPS'!B4:B10,"Camión") -> 0
A35: OCUPACION POR EQUIPO — fuente: GPS real (dias con trip)
A36: Dias habiles del mes (editar c/mes) | B36: =Presupuesto!$B$20 -> 23
A37: Patente | B37: Dias con GPS real (trip) | C37: % Ocupacion (sobre dias habiles)
A38: DVDS36 | B38: =COUNTIF('Datos - GPS Dias'!$A$5:$A$70,A38) -> 17 | C38: =B38/$B$36 -> 0.73913043
A39: GCFF12 | B39: =COUNTIF('Datos - GPS Dias'!$A$5:$A$70,A39) -> 10 | C39: =B39/$B$36 -> 0.43478261
A40: GKFD84 | B40: =COUNTIF('Datos - GPS Dias'!$A$5:$A$70,A40) -> 18 | C40: =B40/$B$36 -> 0.7826087
A41: WR9192 | B41: =COUNTIF('Datos - GPS Dias'!$A$5:$A$70,A41) -> 11 | C41: =B41/$B$36 -> 0.47826087
A42: XR8555 | B42: =COUNTIF('Datos - GPS Dias'!$A$5:$A$70,A42) -> 9 | C42: =B42/$B$36 -> 0.39130435
A43: BPLB35 | B43: 0 | C43: =B43/$B$36 -> 0
A45: CALIDAD: sin fuente de datos disponible -- pendiente definir indicador y origen.

Sheet Datos - Servicios Jul
A1: SERVICIOS REALIZADOS — JULIO 2026 (fuente: planilla de control de Pablo)
A3: Patente | B3: Fecha (Fecha GD real) | C3: Cliente | D3: Origen | E3: Destino | F3: Flete Total (bruto) | G3: Flete Neto (=Bruto/1.19) | H3: Estado Pago | I3: Conductor | J3: Patente normalizada | K3: GPS confirma ese dia | L3: Dia unico conf. GPS x conductor
A4: DSDV36 | B4: 2026-07-02 | C4: Nano Presmita | D4: Coltauco | E4: Valparaiso | F4: 479999.59 | G4: =F4/1.19 -> 403361 | H4: Pendiente | I4: Felipe Madariaga | J4: =IF(A4="DSDV36","DVDS36",A4) -> DVDS36 | K4: =IF(SUMPRODUCT(('Datos - GPS Dias'!$A$5:$A$70=J4)*('Datos - GPS Dias'!$B$5:$B$70=TEXT(B4,"yyyy-mm-dd")))>0,1,0) -> 1 | L4: =IF(AND(COUNTIFS($I$4:I4,I4,$B$4:B4,B4)=1,K4=1),1,0) -> 1
A5: DSDV36 | B5: 2026-07-02 | C5: Nano Presmita | D5: Molino | E5: Coltauco | F5: 40000.66 | G5: =F5/1.19 -> 33614 | H5: Pendiente | I5: Felipe Madariaga | J5: =IF(A5="DSDV36","DVDS36",A5) -> DVDS36 | K5: =IF(SUMPRODUCT(('Datos - GPS Dias'!$A$5:$A$70=J5)*('Datos - GPS Dias'!$B$5:$B$70=TEXT(B5,"yyyy-mm-dd")))>0,1,0) -> 1 | L5: =IF(AND(COUNTIFS($I$4:I5,I5,$B$4:B5,B5)=1,K5=1),1,0) -> 0
A6: DSDV36 | B6: 2026-07-02 | C6: Rata | D6: Peumo | E6: Talca | F6: 380000.32 | G6: =F6/1.19 -> 319328 | H6: Pagado | I6: Nicolas Vega | J6: =IF(A6="DSDV36","DVDS36",A6) -> DVDS36 | K6: =IF(SUMPRODUCT(('Datos - GPS Dias'!$A$5:$A$70=J6)*('Datos - GPS Dias'!$B$5:$B$70=TEXT(B6,"yyyy-mm-dd")))>0,1,0) -> 1 | L6: =IF(AND(COUNTIFS($I$4:I6,I6,$B$4:B6,B6)=1,K6=1),1,0) -> 1
A7: GKFD84 | B7: 2026-07-02 | C7: Sollem | D7: Casa Blanca | E7: Placilla - Chepica | F7: 808248 | G7: =F7/1.19 -> 679200 | H7: Pendiente | I7: Felipe Madariaga | J7: =IF(A7="DSDV36","DVDS36",A7) -> GKFD84 | K7: =IF(SUMPRODUCT(('Datos - GPS Dias'!$A$5:$A$70=J7)*('Datos - GPS Dias'!$B$5:$B$70=TEXT(B7,"yyyy-mm-dd")))>0,1,0) -> 0 | L7: =IF(AND(COUNTIFS($I$4:I7,I7,$B$4:B7,B7)=1,K7=1),1,0) -> 0
A8: GKFD84 | B8: 2026-07-06 | C8: Sollem | D8: Placilla | E8: Casa Blanca | F8: 746368 | G8: =F8/1.19 -> 627200 | H8: Pendiente | I8: Felipe Madariaga | J8: =IF(A8="DSDV36","DVDS36",A8) -> GKFD84 | K8: =IF(SUMPRODUCT(('Datos - GPS Dias'!$A$5:$A$70=J8)*('Datos - GPS Dias'!$B$5:$B$70=TEXT(B8,"yyyy-mm-dd")))>0,1,0) -> 1 | L8: =IF(AND(COUNTIFS($I$4:I8,I8,$B$4:B8,B8)=1,K8=1),1,0) -> 1
A9: DSDV36 | B9: 2026-07-06 | C9: Nano Presmita | D9: Coltauco | E9: Valparaiso | F9: 478500 | G9: =F9/1.19 -> 402100.84 | H9: Pendiente | I9: Manuel Madrid | J9: =IF(A9="DSDV36","DVDS36",A9) -> DVDS36 | K9: =IF(SUMPRODUCT(('Datos - GPS Dias'!$A$5:$A$70=J9)*('Datos - GPS Dias'!$B$5:$B$70=TEXT(B9,"yyyy-mm-dd")))>0,1,0) -> 1 | L9: =IF(AND(COUNTIFS($I$4:I9,I9,$B$4:B9,B9)=1,K9=1),1,0) -> 1
A10: GKFD84 | B10: 2026-07-07 | C10: Sollem | D10: Casa Blanca | E10: Peumo | F10: 609280 | G10: =F10/1.19 -> 512000 | H10: Pendiente | I10: Felipe Madariaga | J10: =IF(A10="DSDV36","DVDS36",A10) -> GKFD84 | K10: =IF(SUMPRODUCT(('Datos - GPS Dias'!$A$5:$A$70=J10)*('Datos - GPS Dias'!$B$5:$B$70=TEXT(B10,"yyyy-mm-dd")))>0,1,0) -> 1 | L10: =IF(AND(COUNTIFS($I$4:I10,I10,$B$4:B10,B10)=1,K10=1),1,0) -> 1
A11: DSDV36 | B11: 2026-07-09 | C11: Nano Presmita | D11: Coltauco | E11: Valparaiso | F11: 478500 | G11: =F11/1.19 -> 402100.84 | H11: Pendiente | I11: Felipe Madariaga | J11: =IF(A11="DSDV36","DVDS36",A11) -> DVDS36 | K11: =IF(SUMPRODUCT(('Datos - GPS Dias'!$A$5:$A$70=J11)*('Datos - GPS Dias'!$B$5:$B$70=TEXT(B11,"yyyy-mm-dd")))>0,1,0) -> 1 | L11: =IF(AND(COUNTIFS($I$4:I11,I11,$B$4:B11,B11)=1,K11=1),1,0) -> 1
A12: DSDV36 | B12: 2026-07-12 | C12: Nano Presmita | D12: Coltauco | E12: Valparaiso | F12: 478500 | G12: =F12/1.19 -> 402100.84 | H12: Pendiente | I12: Manuel Madrid | J12: =IF(A12="DSDV36","DVDS36",A12) -> DVDS36 | K12: =IF(SUMPRODUCT(('Datos - GPS Dias'!$A$5:$A$70=J12)*('Datos - GPS Dias'!$B$5:$B$70=TEXT(B12,"yyyy-mm-dd")))>0,1,0) -> 0 | L12: =IF(AND(COUNTIFS($I$4:I12,I12,$B$4:B12,B12)=1,K12=1),1,0) -> 0
A13: GKFD84 | B13: 2026-07-13 | C13: Sollem | D13: Casa Blanca | E13: Placilla - Santa Cruz - Marchigue | F13: 889168 | G13: =F13/1.19 -> 747200 | H13: Pagado | I13: Felipe Madariaga | J13: =IF(A13="DSDV36","DVDS36",A13) -> GKFD84 | K13: =IF(SUMPRODUCT(('Datos - GPS Dias'!$A$5:$A$70=J13)*('Datos - GPS Dias'!$B$5:$B$70=TEXT(B13,"yyyy-mm-dd")))>0,1,0) -> 1 | L13: =IF(AND(COUNTIFS($I$4:I13,I13,$B$4:B13,B13)=1,K13=1),1,0) -> 1
A14: WR9192 | B14: 2026-07-14 | C14: Sollem | D14: Casa Blanca | E14: Requinoa - Chimbarongo - San Fernando | F14: 889168 | G14: =F14/1.19 -> 747200 | H14: Pagado | I14: Francisco Mancilla | J14: =IF(A14="DSDV36","DVDS36",A14) -> WR9192 | K14: =IF(SUMPRODUCT(('Datos - GPS Dias'!$A$5:$A$70=J14)*('Datos - GPS Dias'!$B$5:$B$70=TEXT(B14,"yyyy-mm-dd")))>0,1,0) -> 1 | L14: =IF(AND(COUNTIFS($I$4:I14,I14,$B$4:B14,B14)=1,K14=1),1,0) -> 1
A15: GKFD84 | B15: 2026-07-14 | C15: Sollem | D15: Casa Blanca | E15: Requinoa | F15: 609280 | G15: =F15/1.19 -> 512000 | H15: Pagado | I15: Felipe Madariaga | J15: =IF(A15="DSDV36","DVDS36",A15) -> GKFD84 | K15: =IF(SUMPRODUCT(('Datos - GPS Dias'!$A$5:$A$70=J15)*('Datos - GPS Dias'!$B$5:$B$70=TEXT(B15,"yyyy-mm-dd")))>0,1,0) -> 1 | L15: =IF(AND(COUNTIFS($I$4:I15,I15,$B$4:B15,B15)=1,K15=1),1,0) -> 1
... A44: GKFD84 | B44: 2026-07-30 | C44: Andrea Alacon | D44: San Felipe | E44: Coltauco | F44: 550000 | G44: =F44/1.19 -> 462184.87 | H44: Pendiente | I44: Felipe Madariaga | J44: =IF(A44="DSDV36","DVDS36",A44) -> GKFD84 | K44: =IF(SUMPRODUCT(('Datos - GPS Dias'!$A$5:$A$70=J44)*('Datos - GPS Dias'!$B$5:$B$70=TEXT(B44,"yyyy-mm-dd")))>0,1,0) -> 1 | L44: =IF(AND(COUNTIFS($I$4:I44,I44,$B$4:B44,B44)=1,K44=1),1,0) -> 1
E45: TOTAL | F45: =SUM(F4:F44) -> 19907384 | G45: =SUM(G4:G44) -> 16728894

Sheet Datos - Cartola Jul
A1: CARTOLA BANCARIA REAL — JULIO 2026 (Banco Santander)
A2: Columnas F y G son EDITABLES (fondo amarillo): completa la patente (para Mantencion/Combustible) y/o el concepto real cuando la categoria sea "otro_por_clasificar".
A4: Fecha | B4: Tipo | C4: Categoria | D4: Monto | E4: Referencia | F4: Patente (si aplica) | G4: Concepto real (si es otro_por_clasificar)
A5: 2026-07-01 | B5: egreso | C5: viatico | D5: 6000 | E5: Transf a Felipe Vidal
A6: 2026-07-01 | B6: egreso | C6: combustible | D6: 1300000 | E6: PAGO EN LINEA ESMAX
A7: 2026-07-01 | B7: ingreso | C7: factoring | D7: 2326472 | E7: Transf GLOBAL SOLUTIONS SPA
A8: 2026-07-01 | B8: egreso | C8: peajes | D8: 15000 | E8: Transf a Felipe Vidal
A9: 2026-07-01 | B9: egreso | C9: viatico | D9: 12000 | E9: Transf a Felipe Vidal
A10: 2026-07-01 | B10: egreso | C10: aporte_retiro_socio | D10: 70000 | E10: Transf a RIQUELME OLEA PABLO
A11: 2026-07-02 | B11: egreso | C11: otro_por_clasificar | D11: 54000 | E11: Transf a Jose Acevedo
A12: 2026-07-02 | B12: egreso | C12: remuneracion_administrativa | D12: 225000 | E12: Transf a Sebastian Zuniga
A13: 2026-07-02 | B13: egreso | C13: otro_por_clasificar | D13: 2700 | E13: TUU Comercial Escorpio
A14: 2026-07-02 | B14: egreso | C14: otro_por_clasificar | D14: 190000 | E14: Transf a Nicolas Carvallo
A15: 2026-07-02 | B15: egreso | C15: otro_por_clasificar | D15: 30000 | E15: Transf a Servicios integrales FYR
A16: 2026-07-03 | B16: egreso | C16: mantencion | D16: 299606 | E16: COMERCIAL RIHE LTDA
... A167: 2026-07-31 | B167: egreso | C167: sueldo_conductor | D167: 6000 | E167: Transf a Francisco Mancilla

Sheet Datos - Combustible y GPS
A1: COMBUSTIBLE REAL (ARAMCO + COPEC) Y KM GPS POR EQUIPO — JULIO 2026
A3: Patente | B3: Tipo equipo | C3: Litros (Aramco) | D3: Monto $ (Aramco, con IVA) | E3: Km recorridos (GPS, evento=trip)
A4: DVDS36 | B4: Camión | C4: 1011 | D4: 1202490 | E4: 3682.959
A5: GCFF12 | B5: Camión | C5: 1235.6 | D5: 1467626 | E5: 2450.405
A6: GKFD84 | B6: Camión | C6: 2605.4 | D6: 3114070 | E6: 5277.71
A7: KSRC78 | B7: Camioneta | C7: 456.8 | D7: 565507 | E7: SIN GPS EN JULIO
A8: WR9192 | B8: Camión | C8: 369.9 | D8: 431517 | E8: 933.913
A9: XR8555 | B9: Camión | C9: 629.9 | D9: 734515 | E9: 1403.627
A10: JYJV21 | B10: Camioneta | C10: 41.1 | D10: 50000 | E10: SIN GPS EN JULIO
A13: Fuente: Aramco + Copec combinados.

Sheet Datos - GPS Dias
A1: DIAS REALES CON MOVIMIENTO GPS (evento=trip) POR EQUIPO — JULIO 2026
A2: DVDS36 = DSDV36 (mismo equipo, confirmado). Fuente de verdad para Ocupacion y Viatico.
A4: Patente | B4: Fecha
A5: DVDS36 | B5: 2026-07-02
A6: DVDS36 | B6: 2026-07-03
A7: DVDS36 | B7: 2026-07-04
A8: DVDS36 | B8: 2026-07-06
A9: DVDS36 | B9: 2026-07-07
A10: DVDS36 | B10: 2026-07-09
A11: DVDS36 | B11: 2026-07-10
A12: DVDS36 | B12: 2026-07-13
A13: DVDS36 | B13: 2026-07-14
A14: DVDS36 | B14: 2026-07-15
A15: DVDS36 | B15: 2026-07-20
... A70: XR8555 | B70: 2026-07-30
